Workbook

Sheet Financial Model
A1: Model Variables | H1: Month to Month Account Growth | I1: 1 | J1: 1 | K1: 1.5 | L1: 1.1 | M1: 1.15 | N1: 1.15 | O1: 1.2 | P1: 1.2 | Q1: 1.2 | R1: 1.3 | S1: 1.3 | T1: 1.3 | U1: 1.15 | V1: 1.15 | W1: 1.2 | X1: 1.2 | Y1: 1.15 | Z1: 1.15 | AA1: 1.15 | AB1: 1.15 | AC1: 1.15 | AD1: 1.15 | AE1: 1.15 | AF1: 1.15 | AG1: 1.15
A2: Average Cost Per Lead | C2: 15 | H2: Contract Account Growth | I2: 1 | J2: 2 | K2: 2 | L2: 0.6 | M2: 1.15 | N2: 1.15 | O2: 1.2 | P2: 1.2 | Q2: 1.2 | R2: 1.3 | S2: 1.3 | T2: 1.4 | U2: 1.15 | V2: 1.15 | W2: 1.15 | X2: 1.15 | Y2: 1.15 | Z2: 1.15 | AA2: 1.15 | AB2: 1.15 | AC2: 1.15 | AD2: 1.15 | AE2: 1.15 | AF2: 1.15 | AG2: 1.15
A3: Average Conversion Rate to Paid Account
A4: Attrition Rate | C4: 0.05
A5: Initial Month Attrition Rate | C5: 0.2 | I5: Jan
I6: Month 1 | J6: Month 2 | K6: Month 3 | L6: Month 4 | M6: Month 5 | N6: Month 6 | O6: Month 7 | P6: Month 8 | Q6: Month 9 | R6: Month 10 | S6: Month 11 | T6: Month 12 | U6: Month 13 | V6: Month 14 | W6: Month 15 | X6: Month 16 | Y6: Month 17 | Z6: Month 18 | AA6: Month 19 | AB6: Month 20 | AC6: Month 21 | AD6: Month 22 | AE6: Month 23 | AF6: Month 24 | AG6: Month 25
H7: Total Customer Count | I7: =I17+I20 -> 18 | J7: =J17+J20 -> 20.65 | K7: =K17+K20 -> 26.0175 | L7: =L17+L20 -> 29.366625 | M7: =M17+M20 -> 33.598294 | N7: =N17+N20 -> 38.473379 | O7: =O17+O20 -> 44.464873 | P7: =P17+P20 -> 51.739824 | ... AG7: =AG17+AG20 -> 929.00079
H8: Total Recurring Monthly Revenue | I8: =I27 -> 13800 | J8: =J27 -> 23765 | K8: =K27 -> 43386.242 | L8: =L27 -> 53119.271 | M8: =M27 -> 64621.847 | N8: =N27 -> 77564.822 | O8: =O27 -> 93090.439 | P8: =P27 -> 111621.66 | ... AG8: =AG27 -> 2225243.2
H9: Total Revenue Collected | I9: =SUM($I$27:I27) -> 13800 | J9: =SUM($J$27:J27) -> 23765 | K9: =SUM(K27:K27) -> 43386.242 | L9: =SUM(L27:L27) -> 53119.271 | M9: =SUM(M27:M27) -> 64621.847 | N9: =SUM(N27:N27) -> 77564.822 | O9: =SUM(O27:O27) -> 93090.439 | P9: =SUM(P27:P27) -> 111621.66 | Q9: =SUM(Q27:Q27) -> 133767.15 | R9: =SUM(R27:R27) -> 163383.17 | ... AG9: =SUM(AG27:AG27) -> 2225243.2
H10: COGS | I10: =I37 -> -13755.92 | J10: =J37 -> -13993.545 | K10: =K37 -> -16362.575 | L10: =L37 -> -17249.869 | M10: =M37 -> -18557.87 | N10: =N37 -> -20030.084 | O10: =O37 -> -22154.147 | P10: =P37 -> -24655.974 | ... AG10: =AG37 -> -253118.09
H11: OpEx | I11: =I61 -> -107642.67 | J11: =J61 -> -138676.39 | K11: =K61 -> -149936.27 | L11: =L61 -> -150636.3 | M11: =M61 -> -155566.8 | N11: =N61 -> -230322.46 | O11: =O61 -> -273681.66 | P11: =P61 -> -330458.75 | ... AG11: =AG61 -> -973439.92
H12: Working Capital | I12: 0 | J12: =I14 -> -107598.59 | K12: =J14 -> -21503.518 | L12: =K14 -> 355583.88 | M12: =L14 -> 300816.98 | N12: =M14 -> 251314.16 | O12: =N14 -> 193526.44 | P12: =O14 -> 140781.07 | Q12: =P14 -> 97288.015 | ... AG12: =AF14 -> 3541856.4
H13: Capital Raise | J13: 215000 | K13: 500000 | L13: 60000 | M13: 60000 | N13: 115000 | O13: 150000 | P13: 200000 | Q13: 200000 | R13: 200000 | S13: =S91*-1 -> 200000 | T13: =T91*-1 -> 200000 | U13: =U91*-1 -> 200000 | V13: =V91*-1 -> 200000 | W13: =W91*-1 -> 200000 | X13: =X91*-1 -> 200000 | Y13: 0 | Z13: 0 | AA13: 0 | AB13: 0 | AC13: 0 | AD13: 0 | AE13: 0 | AF13: 0 | AG13: 0
A14: Current Cost Structure | E14: Cost Per Account Breakdown | H14: Inhouse Capital Requirement | I14: =SUM(I9:I13) -> -107598.59 | J14: =SUM(J9:J13) -> -21503.518 | K14: =SUM(K9:K13) -> 355583.88 | L14: =SUM(L9:L13) -> 300816.98 | M14: =SUM(M9:M13) -> 251314.16 | N14: =SUM(N9:N13) -> 193526.44 | O14: =SUM(O9:O13) -> 140781.07 | P14: =SUM(P9:P13) -> 97288.015 | ... AG14: =SUM(AG9:AG13) -> 4540541.6
H15: Total Creation Multiple
A16: Revenue Summary | E16: New Account Summary | H16: Revenue Summary | I16: 1 | J16: 2 | K16: 3 | L16: 4 | M16: 5 | N16: 6 | O16: 7 | P16: 8 | Q16: 9 | R16: 10 | S16: 11 | T16: 12 | U16: 13 | V16: 14 | W16: 15 | X16: 16 | Y16: 17 | Z16: 18 | AA16: 19 | AB16: 20 | AC16: 21 | AD16: 22 | AE16: 23 | AF16: 24 | AG16: 25
A17: Total Accounts | C17: 15 | E17: Total Accounts | F17: 100 | H17: Total Accounts | I17: =C17 -> 15 | J17: =(I17-(I17*$C$4))+(I20-(I20*$C$5)) -> 16.65 | K17: =(J17-(J17*$C$4))+(J20-(J20*$C$5)) -> 19.0175 | L17: =(K17-(K17*$C$4))+(K20-(K20*$C$5)) -> 23.666625 | M17: =(L17-(L17*$C$4))+(L20-(L20*$C$5)) -> 27.043294 | N17: =(M17-(M17*$C$4))+(M20-(M20*$C$5)) -> 30.935129 | O17: =(N17-(N17*$C$4))+(N20-(N20*$C$5)) -> 35.418973 | P17: =(O17-(O17*$C$4))+(O20-(O20*$C$5)) -> 40.884744 | Q17: =(P17-(P17*$C$4))+(P20-(P20*$C$5)) -> 47.524571 | ... AG17: =(AF17-(AF17*$C$4))+(AF20-(AF20*$C$5)) -> 738.15792
A18: Montly Accounts Sold | C18: 2 | E18: Montly Accounts Sold | F18: 20 | H18: Montly Accounts Sold | I18: =I1*2 -> 2 | J18: =J1*I18 -> 2 | K18: =K1*J18 -> 3 | L18: =L1*K18 -> 3.3 | M18: =M1*L18 -> 3.795 | N18: =N1*M18 -> 4.36425 | O18: =O1*N18 -> 5.2371 | P18: =P1*O18 -> 6.28452 | Q18: =Q1*P18 -> 7.541424 | ... AG18: =AG1*AF18 -> 110.99979
A19: Contract Account Sold | C19: 1 | E19: Contract Account Sold | F19: 4 | H19: Contract Account Sold | I19: =I2*1 -> 1 | J19: =I19*J2 -> 2 | K19: =J19*K2 -> 4 | L19: =K19*L2 -> 2.4 | M19: =L19*M2 -> 2.76 | N19: =M19*N2 -> 3.174 | O19: =N19*O2 -> 3.8088 | P19: =O19*P2 -> 4.57056 | Q19: =P19*Q2 -> 5.484672 | ... AG19: =AF19*AG2 -> 79.843088
A20: Total Paid Accounts Onboarded | C20: 1 | E20: Total Paid Accounts Onboarded | F20: =SUM(F18:F19) -> 24 | H20: Total Paid Accounts Onboarded | I20: =SUM(I18:I19) -> 3 | J20: =SUM(J18:J19) -> 4 | K20: =SUM(K18:K19) -> 7 | L20: =SUM(L18:L19) -> 5.7 | M20: =SUM(M18:M19) -> 6.555 | N20: =SUM(N18:N19) -> 7.53825 | O20: =SUM(O18:O19) -> 9.0459 | P20: =SUM(P18:P19) -> 10.85508 | ... AG20: =SUM(AG18:AG19) -> 190.84288
A21: Average MMR | C21: 520 | E21: Average MMR | F21: 3500 | H21: Average MMR | I21: 520 | J21: =(I27/I7) -> 766.66667 | K21: =(J27/J7) -> 1150.8475 | L21: =(K27/K7) -> 1667.5792 | M21: =(L27/L7) -> 1808.8313 | N21: =(M27/M7) -> 1923.3669 | O21: =(N27/N7) -> 2016.0647 | P21: =(O27/O7) -> 2093.5726 | Q21: =(P27/P7) -> 2157.3646 | ... AG21: =(AF27/AF7) -> 2395.2678
A22: New Month-to-Month Average | C22: 500 | E22: New Month-to-Month Average | F22: 750 | H22: New Month-to-Month Average | I22: 500 | J22: 500 | K22: 500 | L22: 501 | M22: 502 | N22: 503 | O22: 504 | P22: 505 | Q22: 506 | R22: 507 | S22: 508 | T22: 509 | U22: 510 | V22: 511 | W22: 512 | X22: 513 | Y22: 514 | Z22: 515 | AA22: 516 | AB22: 517 | AC22: 518 | AD22: 519 | AE22: 520 | AF22: 521 | AG22: 522
A23: New Contract Average | C23: 7500 | E23: New Contract Average | F23: 6500 | H23: New Contract Average | I23: =5000 -> 5000 | J23: =5000 -> 5000 | K23: =5000 -> 5000 | L23: =5000 -> 5000 | M23: =5000 -> 5000 | N23: =5000 -> 5000 | O23: =5000 -> 5000 | P23: =5000 -> 5000 | ... AG23: =5000 -> 5000
A24: New Montly Account Revenue | C24: =(C23*C19)+(C18*C22) -> 8500 | E24: New Montly Account Revenue | F24: =(F23*F19)+(F18*F22) -> 41000 | H24: New Montly Account Revenue | I24: =(I23*I19)+(I18*I22) -> 6000 | J24: =(J23*J19)+(J18*J22) -> 11000 | K24: =K22*K18+(K23*K19) -> 21500 | L24: =L22*L18+(L23*L19) -> 13653.3 | M24: =M22*M18+(M23*M19) -> 15705.09 | N24: =N22*N18+(N23*N19) -> 18065.218 | O24: =O22*O18+(O23*O19) -> 21683.498 | P24: =P22*P18+(P23*P19) -> 26026.483 | Q24: =Q22*Q18+(Q23*Q19) -> 31239.321 | R24: =R22*R18+(R23*R19) -> 40620.921 | ... AG24: =AG22*AG18+(AG23*AG19) -> 457157.33
F25: =F23*F19+(F24*F20) -> 1010000
A26: New Account Revenue | C26: =SUM(C24:C25) -> 8500 | E26: New Account Revenue | H26: New Account Revenue | I26: =SUM(I24:I25) -> 6000 | J26: =SUM(J24:J25) -> 11000 | K26: =SUM(K24:K25) -> 21500 | L26: =SUM(L24:L25) -> 13653.3 | M26: =SUM(M24:M25) -> 15705.09 | N26: =SUM(N24:N25) -> 18065.218 | O26: =SUM(O24:O25) -> 21683.498 | P26: =SUM(P24:P25) -> 26026.483 | ... AG26: =SUM(AG24:AG25) -> 457157.33
A27: Total Monthly Revenue | C27: =C26+(C17*C21) -> 16300 | E27: Total Monthly Revenue | F27: =SUM(F25:F26) -> 1010000 | H27: Total Monthly Revenue | I27: =I26+I17*I21 -> 13800 | J27: =J26+(J17*J21) -> 23765 | K27: =K26+(K17*K21) -> 43386.242 | L27: =L26+(L17*L21) -> 53119.271 | M27: =M26+(M17*M21) -> 64621.847 | N27: =N26+(N17*N21) -> 77564.822 | O27: =O26+(O17*O21) -> 93090.439 | P27: =P26+(P17*P21) -> 111621.66 | Q27: =Q26+(Q17*Q21) -> 133767.15 | ... AG27: =AG26+(AG17*AG21) -> 2225243.2
A29: Gross Profit | C29: =C27+C37 -> 6415.67 | E29: Net Operating Income | H29: Gross Profit | I29: =I27+I37 -> 44.08 | J29: =J27+J37 -> 9771.4553 | K29: =K27+K37 -> 27023.666 | L29: =L27+L37 -> 35869.402 | M29: =M27+M37 -> 46063.977 | N29: =N27+N37 -> 57534.737 | O29: =O27+O37 -> 70936.292 | P29: =P27+P37 -> 86965.689 | ... AG29: =AG27+AG37 -> 1972125.1
A31: COGS | E31: COGS | H31: COGS
A32: Cloud Services | C32: -3162.95 | E32: Cloud Services | H32: Cloud Services | I32: =-3162.95*I65 -> -6325.9 | J32: =I32*J65 -> -6484.0475 | K32: =J32*K65 -> -6646.1487 | L32: =K32*L65 -> -6812.3024 | M32: =L32*M65 -> -6982.61 | N32: =M32*N65 -> -7157.1752 | O32: =N32*O65 -> -7336.1046 | P32: =O32*P65 -> -7519.5072 | Q32: =P32*Q65 -> -7707.4949 | ... AG32: =AF32*AG65 -> -11441.819
A33: Software - COGS | C33: -2093.47 | E33: Software - COGS | H33: Software - COGS | I33: -2093.47 | J33: =I33*J66 -> -2145.8067 | K33: =J33*K66 -> -2199.4519 | L33: =K33*L66 -> -2254.4382 | M33: =L33*M66 -> -2310.7992 | N33: =M33*N66 -> -2368.5692 | O33: =N33*O66 -> -2427.7834 | P33: =O33*P66 -> -2488.478 | Q33: =P33*Q66 -> -2550.6899 | ... AG33: =AF33*AG66 -> -3786.5135
A34: Software - Tools | C34: -1085.62 | E34: Software - Tools | H34: Software - Tools | I34: -1085.62 | J34: =I34*J67 -> -1112.7605 | K34: =J34*K67 -> -1140.5795 | L34: =K34*L67 -> -1169.094 | M34: =L34*M67 -> -1198.3214 | N34: =M34*N67 -> -1228.2794 | O34: =N34*O67 -> -1258.9864 | P34: =O34*P67 -> -1290.461 | Q34: =P34*Q67 -> -1322.7226 | ... AG34: =AF34*AG67 -> -1963.5891
A35: Voice AI Provider | C35: -708.64 | E35: Voice AI Provider | H35: Voice AI Provider | I35: =-708.64*I68 -> -1417.28 | J35: =I35*J68 -> -1417.28 | K35: =J35*K68 -> -2125.92 | L35: =K35*L68 -> -2338.512 | M35: =L35*M68 -> -2689.2888 | N35: =M35*N68 -> -3092.6821 | O35: =N35*O68 -> -3711.2185 | P35: =O35*P68 -> -4453.4623 | Q35: =P35*Q68 -> -5344.1547 | ... AG35: =AF35*AG68 -> -78658.89
A36: Telephony Carriers | C36: -2833.65 | E36: Telephony Carriers | H36: Telephony Carriers | I36: -2833.65 | J36: =I36*J69 -> -2833.65 | K36: =J36*K69 -> -4250.475 | L36: =K36*L69 -> -4675.5225 | M36: =L36*M69 -> -5376.8509 | N36: =M36*N69 -> -6183.3785 | O36: =N36*O69 -> -7420.0542 | P36: =O36*P69 -> -8904.065 | Q36: =P36*Q69 -> -10684.878 | ... AG36: =AF36*AG69 -> -157267.28
A37: Total COGS | C37: =SUM(C32:C36) -> -9884.33 | D37: 0 | E37: Total COGS | F37: =C37/$C$20 -> -9884.33 | H37: Total COGS | I37: =SUM(I32:I36) -> -13755.92 | J37: =SUM(J32:J36) -> -13993.545 | K37: =SUM(K32:K36) -> -16362.575 | L37: =SUM(L32:L36) -> -17249.869 | M37: =SUM(M32:M36) -> -18557.87 | N37: =SUM(N32:N36) -> -20030.084 | O37: =SUM(O32:O36) -> -22154.147 | P37: =SUM(P32:P36) -> -24655.974 | ... AG37: =SUM(AG32:AG36) -> -253118.09
A40: Operating Costs | E40: Operating Costs Per Sale | H40: Operating Costs
A41: Bank Service Charges | C41: -250 | D41: 1 | E41: Bank Service Charges | F41: =C41/$C$20 -> -250 | H41: Bank Service Charges | I41: =C41 -> -250 | J41: =I41*J72 -> -250 | K41: =J41*K72 -> -250 | L41: =K41*L72 -> -250 | M41: =L41*M72 -> -250 | N41: =M41*N72 -> -250 | O41: =N41*O72 -> -250 | P41: =O41*P72 -> -250 | Q41: =P41*Q72 -> -250 | ... AG41: =AF41*AG72 -> -250
A42: Total Dev Contract labor | C42: -53804.906 | D42: 1 | E42: Total Contract labor | F42: =C42/$C$20 -> -53804.906 | H42: Total Contract labor | I42: =$C$42*I73 -> -67256.133 | J42: =I42*J73 -> -70618.94 | K42: =J42*K73 -> -74149.887 | L42: =K42*L73 -> -77857.381 | M42: =L42*M73 -> -85643.119 | N42: =M42*N73 -> -94207.431 | O42: =N42*O73 -> -103628.17 | P42: =O42*P73 -> -113990.99 | Q42: =P42*Q73 -> -119690.54 | ... AG42: =AF42*AG73 -> -181798.48
A43: Lincense and Subscription Fees | C43: -121.36364 | D43: 1 | E43: Lincense and Subscription Fees | F43: =C43/$C$20 -> -121.36364 | H43: Lincense and Subscription Fees | I43: =C43 -> -121.36364 | J43: =I43*J74 -> -124.39773 | K43: =J43*K74 -> -127.50767 | L43: =K43*L74 -> -130.69536 | M43: =L43*M74 -> -133.96275 | N43: =M43*N74 -> -137.31181 | O43: =N43*O74 -> -140.74461 | P43: =O43*P74 -> -144.26323 | Q43: =P43*Q74 -> -147.86981 | ... AG43: =AF43*AG74 -> -219.51356
A44: Software & apps | C44: -4477.18 | E44: Software & apps | H44: Software & apps | I44: =C44 -> -4477.18 | J44: =I44*J75 -> -4589.1095 | K44: =J44*K75 -> -4703.8372 | L44: =K44*L75 -> -4821.4332 | M44: =L44*M75 -> -4941.969 | N44: =M44*N75 -> -5065.5182 | O44: =N44*O75 -> -5192.1562 | P44: =O44*P75 -> -5321.9601 | Q44: =P44*Q75 -> -5455.0091 | ... AG44: =AF44*AG75 -> -8097.9916
A45: Ai Software Tools - Not COGS | C45: -237.99 | E45: Ai Software Tools - Not COGS | H45: Ai Software Tools - Not COGS | I45: =C45 -> -237.99 | J45: =I45*J76 -> -243.93975 | K45: =J45*K76 -> -250.03824 | L45: =K45*L76 -> -256.2892 | M45: =L45*M76 -> -262.69643 | N45: =M45*N76 -> -269.26384 | O45: =N45*O76 -> -275.99544 | P45: =O45*P76 -> -282.89532 | Q45: =P45*Q76 -> -289.96771 | ... AG45: =AF45*AG76 -> -430.45869
A46: R&D Deve | C46: 0 | E46: R&D Deve | H46: R&D Deve | I46: =I77*1 -> 0 | J46: =J77*1 -> 0 | K46: =K77*1 -> 0 | L46: =L77*1 -> 0 | M46: =M77*1 -> 0 | N46: =N77*1 -> 0 | O46: =O77*1 -> 0 | P46: =P77*1 -> 0 | ... AG46: =AG77*1 -> 0
A47: Exec Comp | C47: 0 | E47: Exec Comp | H47: Exec Comp | I47: -25000 | J47: =I47*J78 -> -50000 | K47: =J47*K78 -> -50000 | L47: =K47*L78 -> -50000 | M47: =L47*M78 -> -50000 | N47: =M47*N78 -> -110000 | O47: =N47*O78 -> -132000 | P47: =O47*P78 -> -165000 | Q47: =P47*Q78 -> -165000 | ... AG47: =AF47*AG78 -> -232171.57
A49: Lead Cost | E49: Lead Cost | F49: -500 | H49: Lead Cost | I49: =$F$49*I20 -> -1500 | J49: =$F$49*J20 -> -2000 | K49: =$F$49*K20 -> -3500 | L49: =$F$49*L20 -> -2850 | M49: =$F$49*M20 -> -3277.5 | N49: =$F$49*N20 -> -3769.125 | O49: =$F$49*O20 -> -4522.95 | P49: =$F$49*P20 -> -5427.54 | ... AG49: =$F$49*AG20 -> -95421.438
A50: Sales Rep Payroll | E50: Sales Rep Payroll | F50: -500 | H50: Sales Rep Payroll | I50: =$F$50*I20 -> -1500 | J50: =$F$50*J20 -> -2000 | K50: =$F$50*K20 -> -3500 | L50: =$F$50*L20 -> -2850 | M50: =$F$50*M20 -> -3277.5 | N50: =$F$50*N20 -> -3769.125 | O50: =$F$50*O20 -> -4522.95 | P50: =$F$50*P20 -> -5427.54 | ... AG50: =$F$50*AG20 -> -95421.438
A51: Sales Admin | E51: Sales Admin | F51: -750 | H51: Sales Admin | I51: =$F$51*I20 -> -2250 | J51: =$F$51*J20 -> -3000 | K51: =$F$51*K20 -> -5250 | L51: =$F$51*L20 -> -4275 | M51: =$F$51*M20 -> -4916.25 | N51: =$F$51*N20 -> -5653.6875 | O51: =$F$51*O20 -> -6784.425 | P51: =$F$51*P20 -> -8141.31 | ... AG51: =$F$51*AG20 -> -143132.16
A52: Customer Success | E52: Customer Success | F52: -750 | H52: Customer Success | I52: =$F$52*I20 -> -2250 | J52: =$F$52*J20 -> -3000 | K52: =$F$52*K20 -> -5250 | L52: =$F$52*L20 -> -4275 | M52: =$F$52*M20 -> -4916.25 | N52: =$F$52*N20 -> -5653.6875 | O52: =$F$52*O20 -> -6784.425 | P52: =$F$52*P20 -> -8141.31 | ... AG52: =$F$52*AG20 -> -143132.16
A54: Total Legal & accounting services | C54: -1800 | E54: Total Legal & accounting services | H54: Total Legal & accounting services | I54: =-1800*I81 -> -1800 | J54: =-1800*J81 -> -1800 | K54: =-1800*K81 -> -1800 | L54: =-1800*L81 -> -1800 | M54: =-1800*M81 -> -1800 | N54: =-1800*N81 -> -2700 | O54: =-N54*O81 -> 3240 | P54: =-O54*P81 -> -3888 | Q54: =-P54*Q81 -> 4665.6 | R54: =-Q54*R81 -> -5598.72 | S54: =-R54*S81 -> 5598.72 | T54: =-S54*T81 -> -5598.72 | U54: =-T54*U81 -> 5598.72 | V54: =-U54*V81 -> -5598.72 | ... AG54: =-AF54*AG81 -> 5598.72
A55: Health Insurance Expense | C55: 0 | D55: 1 | E55: Health Insurance Expense | F55: =C55/$C$20 -> 0 | H55: Health Insurance Expense | I55: =$F55*I$20 -> 0 | J55: =$F55*J$20 -> 0 | K55: =$F55*K$20 -> 0 | L55: =$F55*L$20 -> 0 | M55: =$F55*M$20 -> 0 | N55: =N82 -> 3 | O55: =O82 -> -13303.198 | P55: =P82 -> -14142.069 | Q55: =Q82 -> -14744.564 | R55: =R82 -> -15572.575 | S55: =S82 -> -15572.575 | T55: =T82 -> -15572.575 | U55: =U82 -> -15572.575 | ... AG55: =AG82 -> -15572.575
A56: Work Comp and Liability Insurance | C56: 0 | D56: 1 | E56: Work Comp and Liability Insurance | F56: =C56/$C$20 -> 0 | H56: Work Comp and Liability Insurance | I56: =$F56*I$20 -> 0 | J56: =$F56*J$20 -> 0 | K56: =$F56*K$20 -> 0 | L56: =$F56*L$20 -> 0 | M56: =$F56*M$20 -> 0 | N56: =SUM(N50:N52)*0.17 -> -2563.005 | O56: =SUM(O50:O52)*0.17 -> -3075.606 | P56: =SUM(P50:P52)*0.17 -> -3690.7272 | Q56: =SUM(Q50:Q52)*0.17 -> -4428.8726 | R56: =SUM(R50:R52)*0.17 -> -5757.5344 | S56: =SUM(S50:S52)*0.17 -> -7484.7948 | T56: =SUM(T50:T52)*0.17 -> -10045.382 | U56: =SUM(U50:U52)*0.17 -> -11552.19 | ... AG56: =SUM(AG50:AG52)*0.17 -> -64886.578
A57: Meals and Entertainment | C57: -500 | D57: 1 | E57: Meals and Entertainment | F57: =C57/$C$20 -> -500 | H57: Meals and Entertainment | I57: =F57*I85 -> -1000 | J57: =I57*J85 -> -1050 | K57: =J57*K85 -> -1155 | L57: =K57*L85 -> -1270.5 | M57: =L57*M85 -> -1397.55 | N57: =M57*N85 -> -1537.305 | O57: =N57*O85 -> -1691.0355 | P57: =O57*P85 -> -1860.1391 | Q57: =P57*Q85 -> -2046.153 | ... AG57: =AF57*AG85 -> -3754.2778
A58: Office Supplies | C58: 0 | D58: 1 | E58: Office Supplies | F58: =C58/$C$20 -> 0 | H58: Office Supplies | I58: =$F58*I$20 -> 0 | J58: =$F58*J$20 -> 0 | K58: =$F58*K$20 -> 0 | L58: =$F58*L$20 -> 0 | M58: =M88 -> 250 | N58: =M58*N88 -> 250 | O58: =N58*O88 -> 250 | P58: =O58*P88 -> 250 | Q58: =P58*Q88 -> 250 | R58: =Q58*R88 -> 250 | S58: =R58*S88 -> 250 | T58: =S58*T88 -> 250 | U58: =T58*U88 -> 250 | ... AG58: =AF58*AG88 -> 250
A59: Rent Expense | C59: 0 | E59: Rent Expense | F59: =C59/$C$20 -> 0 | H59: Rent Expense | I59: =$F59*I$20 -> 0 | J59: =$F59*J$20 -> 0 | K59: =$F59*K$20 -> 0 | L59: =$F59*L$20 -> 0 | M59: =M89 -> 5000 | N59: =M59*N89 -> 5000 | O59: =N59*O89 -> 5000 | P59: =O59*P89 -> 5000 | Q59: =P59*Q89 -> 5000 | R59: =Q59*R89 -> 5000 | S59: =R59*S89 -> 5000 | T59: =S59*T89 -> 5000 | U59: =T59*U89 -> 5000 | ... AG59: =AF59*AG89 -> 5000
A61: Total Operating Costs | C61: =SUM(C41:C60) -> -61191.44 | E61: Total Operating Costs | F61: =SUM(F41:F60) -> -57176.27 | H61: Total Operating Costs | I61: =SUM(I41:I60) -> -107642.67 | J61: =SUM(J41:J60) -> -138676.39 | K61: =SUM(K41:K60) -> -149936.27 | L61: =SUM(L41:L60) -> -150636.3 | M61: =SUM(M41:M60) -> -155566.8 | N61: =SUM(N41:N60) -> -230322.46 | O61: =SUM(O41:O60) -> -273681.66 | P61: =SUM(P41:P60) -> -330458.75 | ... AG61: =SUM(AG41:AG60) -> -973439.92
I62: =(I27+I61)/I27 -> -6.8001932 | J62: =(J27+J61)/J27 -> -4.8353203 | K62: =(K27+K61)/K27 -> -2.4558483 | L62: =(L27+L61)/L27 -> -1.8358126 | M62: =(M27+M61)/M27 -> -1.4073406 | N62: =(N27+N61)/N27 -> -1.9694191 | O62: =(O27+O61)/O27 -> -1.9399545 | P62: =(P27+P61)/P27 -> -1.9605252 | ... AG62: =(AG27+AG61)/AG27 -> 0.56254674
H65: Cloud Services | I65: 2 | J65: 1.025 | K65: 1.025 | L65: 1.025 | M65: 1.025 | N65: 1.025 | O65: 1.025 | P65: 1.025 | Q65: 1.025 | R65: 1.025 | S65: 1.025 | T65: 1.025 | U65: 1.025 | V65: 1.025 | W65: 1.025 | X65: 1.025 | Y65: 1.025 | Z65: 1.025 | AA65: 1.025 | AB65: 1.025 | AC65: 1.025 | AD65: 1.025 | AE65: 1.025 | AF65: 1.025 | AG65: 1.025
H66: Software - COGS | I66: 1 | J66: 1.025 | K66: 1.025 | L66: 1.025 | M66: 1.025 | N66: 1.025 | O66: 1.025 | P66: 1.025 | Q66: 1.025 | R66: 1.025 | S66: 1.025 | T66: 1.025 | U66: 1.025 | V66: 1.025 | W66: 1.025 | X66: 1.025 | Y66: 1.025 | Z66: 1.025 | AA66: 1.025 | AB66: 1.025 | AC66: 1.025 | AD66: 1.025 | AE66: 1.025 | AF66: 1.025 | AG66: 1.025
H67: Software - Tools | I67: 1 | J67: 1.025 | K67: 1.025 | L67: 1.025 | M67: 1.025 | N67: 1.025 | O67: 1.025 | P67: 1.025 | Q67: 1.025 | R67: 1.025 | S67: 1.025 | T67: 1.025 | U67: 1.025 | V67: 1.025 | W67: 1.025 | X67: 1.025 | Y67: 1.025 | Z67: 1.025 | AA67: 1.025 | AB67: 1.025 | AC67: 1.025 | AD67: 1.025 | AE67: 1.025 | AF67: 1.025 | AG67: 1.025
H68: Voice AI Provider | I68: 2 | J68: =J1 -> 1 | K68: =K1 -> 1.5 | L68: =L1 -> 1.1 | M68: =M1 -> 1.15 | N68: =N1 -> 1.15 | O68: =O1 -> 1.2 | P68: =P1 -> 1.2 | Q68: =Q1 -> 1.2 | ... AG68: =AG1 -> 1.15
H69: Telephony Carriers | I69: 1 | J69: =J1 -> 1 | K69: =K1 -> 1.5 | L69: =L1 -> 1.1 | M69: =M1 -> 1.15 | N69: =N1 -> 1.15 | O69: =O1 -> 1.2 | P69: =P1 -> 1.2 | Q69: =Q1 -> 1.2 | ... AG69: =AG1 -> 1.15
H72: Bank Service Charges | I72: 1 | J72: 1 | K72: 1 | L72: 1 | M72: 1 | N72: 1 | O72: 1 | P72: 1 | Q72: 1 | R72: 1 | S72: 1 | T72: 1 | U72: 1 | V72: 1 | W72: 1 | X72: 1 | Y72: 1 | Z72: 1 | AA72: 1 | AB72: 1 | AC72: 1 | AD72: 1 | AE72: 1 | AF72: 1 | AG72: 1
H73: Total Contract labor | I73: 1.25 | J73: 1.05 | K73: 1.05 | L73: 1.05 | M73: 1.1 | N73: 1.1 | O73: 1.1 | P73: 1.1 | Q73: 1.05 | R73: 1.05 | S73: 1.05 | T73: 1.05 | U73: 1 | V73: 1 | W73: 1.025 | X73: 1.025 | Y73: 1.025 | Z73: 1.025 | AA73: 1.025 | AB73: 1.025 | AC73: 1.025 | AD73: 1.025 | AE73: 1.025 | AF73: 1.025 | AG73: 1.025
H74: Lincense and Subscription Fees | I74: 1 | J74: 1.025 | K74: 1.025 | L74: 1.025 | M74: 1.025 | N74: 1.025 | O74: 1.025 | P74: 1.025 | Q74: 1.025 | R74: 1.025 | S74: 1.025 | T74: 1.025 | U74: 1.025 | V74: 1.025 | W74: 1.025 | X74: 1.025 | Y74: 1.025 | Z74: 1.025 | AA74: 1.025 | AB74: 1.025 | AC74: 1.025 | AD74: 1.025 | AE74: 1.025 | AF74: 1.025 | AG74: 1.025
H75: Software & apps | I75: 1 | J75: 1.025 | K75: 1.025 | L75: 1.025 | M75: 1.025 | N75: 1.025 | O75: 1.025 | P75: 1.025 | Q75: 1.025 | R75: 1.025 | S75: 1.025 | T75: 1.025 | U75: 1.025 | V75: 1.025 | W75: 1.025 | X75: 1.025 | Y75: 1.025 | Z75: 1.025 | AA75: 1.025 | AB75: 1.025 | AC75: 1.025 | AD75: 1.025 | AE75: 1.025 | AF75: 1.025 | AG75: 1.025
H76: Ai Software Tools - Not COGS | I76: 1 | J76: 1.025 | K76: 1.025 | L76: 1.025 | M76: 1.025 | N76: 1.025 | O76: 1.025 | P76: 1.025 | Q76: 1.025 | R76: 1.025 | S76: 1.025 | T76: 1.025 | U76: 1.025 | V76: 1.025 | W76: 1.025 | X76: 1.025 | Y76: 1.025 | Z76: 1.025 | AA76: 1.025 | AB76: 1.025 | AC76: 1.025 | AD76: 1.025 | AE76: 1.025 | AF76: 1.025 | AG76: 1.025
H77: R&D Deve | I77: 0 | J77: 0 | K77: 0 | L77: 0 | M77: 0 | N77: 0 | O77: 0 | P77: 0 | Q77: 0 | R77: 0 | S77: 0 | T77: 0 | U77: 0 | V77: 0 | W77: 0 | X77: 0 | Y77: 0 | Z77: 0 | AA77: 0 | AB77: 0 | AC77: 0 | AD77: 0 | AE77: 0 | AF77: 0 | AG77: 0
H78: Exec Comp | I78: 1 | J78: =J2 -> 2 | K78: 1 | L78: 1 | M78: 1 | N78: 2.2 | O78: =O2 -> 1.2 | P78: 1.25 | Q78: 1 | R78: 1 | S78: 1 | T78: 1 | U78: 1 | V78: 1 | W78: 1 | X78: 1 | Y78: 1 | Z78: 1 | AA78: 1.05 | AB78: 1.05 | AC78: 1.05 | AD78: 1.05 | AE78: 1.05 | AF78: 1.05 | AG78: 1.05
H81: Total Legal & accounting services | I81: 1 | J81: 1 | K81: 1 | L81: 1 | M81: 1 | N81: 1.5 | O81: 1.2 | P81: 1.2 | Q81: 1.2 | R81: 1.2 | S81: 1 | T81: 1 | U81: 1 | V81: 1 | W81: 1 | X81: 1 | Y81: 1 | Z81: 1 | AA81: 1 | AB81: 1 | AC81: 1 | AD81: 1 | AE81: 1 | AF81: 1 | AG81: 1
H82: Health Insurance Expense | I82: 0 | J82: 0 | K82: 0 | L82: 0 | M82: 0 | N82: 3 | O82: =(SUM(O42,O50,O51,O52)*0.06)-6000 -> -13303.198 | P82: =(SUM(P42,P50,P51,P52)*0.06)-6000 -> -14142.069 | Q82: =(SUM(Q42,Q50,Q51,Q52)*0.06)-6000 -> -14744.564 | R82: =(SUM(R42,R50,R51,R52)*0.06)-6000 -> -15572.575 | S82: =R82 -> -15572.575 | T82: =S82 -> -15572.575 | U82: =T82 -> -15572.575 | V82: =U82 -> -15572.575 | W82: =V82 -> -15572.575 | X82: =W82 -> -15572.575 | Y82: =X82 -> -15572.575 | Z82: =Y82 -> -15572.575 | ... AG82: =AF82 -> -15572.575
H83: Work Comp and Liability Insurance | I83: 0 | J83: 0 | K83: 0 | L83: 0 | M83: 0 | N83: 0 | O83: 0 | P83: 0 | Q83: 0 | R83: 0 | S83: 0 | T83: 0 | U83: 0 | V83: 0 | W83: 0 | X83: 0 | Y83: 0 | Z83: 0 | AA83: 0 | AB83: 0 | AC83: 0 | AD83: 0 | AE83: 0 | AF83: 0 | AG83: 0
H84: Lincense and Subscription Fees | I84: 1 | J84: 1 | K84: 1 | L84: 1 | M84: 1 | N84: 1 | O84: 1 | P84: 1 | Q84: 1 | R84: 1 | S84: 1 | T84: 1 | U84: 1 | V84: 1 | W84: 1 | X84: 1 | Y84: 1 | Z84: 1 | AA84: 1 | AB84: 1 | AC84: 1 | AD84: 1 | AE84: 1 | AF84: 1 | AG84: 1
H85: Meals and Entertainment | I85: 2 | J85: 1.05 | K85: 1.1 | L85: 1.1 | M85: 1.1 | N85: 1.1 | O85: 1.1 | P85: 1.1 | Q85: 1.1 | R85: 1.1 | S85: 1.1 | T85: 1.1 | U85: 1.025 | V85: 1.025 | W85: 1.025 | X85: 1.025 | Y85: 1.025 | Z85: 1.025 | AA85: 1.025 | AB85: 1.025 | AC85: 1.025 | AD85: 1.025 | AE85: 1.025 | AF85: 1.025 | AG85: 1.025
H86: Office Supplies
H87: Payroll Expense
H88: US Dev Payroll | M88: 250 | N88: 1 | O88: 1 | P88: 1 | Q88: 1 | R88: 1 | S88: 1 | T88: 1 | U88: 1 | V88: 1 | W88: 1 | X88: 1 | Y88: 1 | Z88: 1 | AA88: 1 | AB88: 1 | AC88: 1 | AD88: 1 | AE88: 1 | AF88: 1 | AG88: 1
H89: Rent Expense | M89: 5000 | N89: 1 | O89: 1 | P89: 1 | Q89: 1 | R89: 1 | S89: 1 | T89: 1 | U89: 1 | V89: 1 | W89: 1 | X89: 1 | Y89: 1 | Z89: 1 | AA89: 1 | AB89: 1 | AC89: 1 | AD89: 1 | AE89: 1 | AF89: 1 | AG89: 1
L91: -60000 | M91: -60000 | N91: -115000 | O91: -150000 | P91: -200000 | Q91: -200000 | R91: -200000 | S91: -200000 | T91: -200000 | U91: -200000 | V91: -200000 | W91: -200000 | X91: -200000 | Y91: -200000
L93: =L61-L91 -> -90636.299 | M93: =M61-M91 -> -95566.797 | N93: =N61-N91 -> -115322.46 | O93: =O61-O91 -> -123681.66 | P93: =P61-P91 -> -130458.75 | Q93: =Q61-Q91 -> -134702.62 | R93: =R61-R91 -> -163229.65 | S93: =S61-S91 -> -173119.74 | ... Y93: =Y61-Y91 -> -306624.23

Sheet Current Payroll
B2: Full Monthly Payroll | C2: country
A3: Kyle Nadauld | B3: 5200 | C3: US
A4: Daniel McConnell | B4: 3000 | C4: US
A5: Jonathan Gibby | B5: 7000.13 | C5: US
A6: Tyler (TK) Karren | B6: 5200 | C6: US
A9: Nikola Knežević | B9: 10400 | C9: SERB
A10: Sebastian | B10: 8666.67 | C10: SERB
A11: Nebojsa Krstovic | B11: 3813.33 | C11: SERB
A12: QA Marco | B12: 3466.67 | C12: SERB
A13: Iva Lukac | B13: 1733.33 | C13: SERB
A14: Todor Mihajlovic | B14: 8666.67 | C14: SERB
A17: Gabriel Ceniza | B17: 2894.74
A18: Jenriel Jadraque | B18: 2368.42
A19: Ariel Manayon | B19: 4200
B20: =SUM(B3:B19) -> 66609.96

Sheet Growth Analysis
A1: month | B1: phase | C1: mrr | D1: arr | E1: momGrowth | F1: customers | G1: netNewCustomers | H1: churnRate | I1: arpu | J1: cac | K1: ltv | L1: ltvCacRatio | M1: grossMargin | N1: netBurn | O1: burnMultiple | P1: rule40Score | Q1: cogs | R1: burn | S1: expansionRevenue | T1: netRevenueRetention
A2: 1 | B2: Phase 1 | C2: 22770 | D2: 273240 | E2: 0.15 | F2: 24 | G2: 2 | H2: 0.05 | I2: 949 | J2: 15115 | K2: 227700 | L2: 15.1x | M2: 0.6 | N2: 90594 | O2: 30.5 | P2: 75 | Q2: 9108 | R2: 113364 | S2: 1584 | T2: 1.03 | W2: =R2/O2 -> 3716.8525
A3: 2 | B3: Phase 1 | C3: 26185 | D3: 314226 | E3: 0.15 | F3: 27 | G3: 3 | H3: 0.05 | I3: 970 | J3: 15115 | K3: 232760 | L3: 15.4x | M3: 0.6 | N3: 87179 | O3: 25.52 | P3: 75 | Q3: 10474 | R3: 113364 | S3: 1822 | T3: 1.03
A4: 3 | B4: Phase 1 | C4: 30113 | D4: 361360 | E4: 0.15 | F4: 31 | G4: 4 | H4: 0.05 | I4: 971 | J4: 11336 | K4: 233135 | L4: 20.6x | M4: 0.6 | N4: 83251 | O4: 21.2 | P4: 75 | Q4: 12045 | R4: 113364 | S4: 2095 | T4: 1.03
A5: 4 | B5: Phase 1 | C5: 34630 | D5: 415564 | E5: 0.15 | F5: 35 | G5: 4 | H5: 0.05 | I5: 989 | J5: 11336 | K5: 237465 | L5: 20.9x | M5: 0.6 | N5: 78734 | O5: 17.43 | P5: 75 | Q5: 13852 | R5: 113364 | S5: 2409 | T5: 1.03
A6: 5 | B6: Phase 1 | C6: 39825 | D6: 477898 | E6: 0.15 | F6: 40 | G6: 5 | H6: 0.05 | I6: 996 | J6: 9069 | K6: 238949 | L6: 26.3x | M6: 0.6 | N6: 73539 | O6: 14.16 | P6: 75 | Q6: 15930 | R6: 113364 | S6: 2770 | T6: 1.03
A7: 6 | B7: Phase 1 | C7: 45799 | D7: 549583 | E7: 0.15 | F7: 46 | G7: 6 | H7: 0.05 | I7: 996 | J7: 7558 | K7: 238949 | L7: 31.6x | M7: 0.6 | N7: 67566 | O7: 11.31 | P7: 75 | Q7: 18319 | R7: 113364 | S7: 3186 | T7: 1.03
A8: 7 | B8: Phase 1 | C8: 52668 | D8: 632021 | E8: 0.15 | F8: 52 | G8: 6 | H8: 0.05 | I8: 1013 | J8: 7558 | K8: 243085 | L8: 32.2x | M8: 0.6 | N8: 60696 | O8: 8.84 | P8: 75 | Q8: 21067 | R8: 113364 | S8: 3664 | T8: 1.03
A9: 8 | B9: Phase 1 | C9: 60569 | D9: 726824 | E9: 0.15 | F9: 59 | G9: 7 | H9: 0.05 | I9: 1027 | J9: 6478 | K9: 246381 | L9: 38.0x | M9: 0.6 | N9: 52796 | O9: 6.68 | P9: 75 | Q9: 24227 | R9: 113364 | S9: 4213 | T9: 1.03
A10: 9 | B10: Phase 1 | C10: 69654 | D10: 835847 | E10: 0.15 | F10: 67 | G10: 8 | H10: 0.05 | I10: 1040 | J10: 5668 | K10: 249507 | L10: 44.0x | M10: 0.6 | N10: 43710 | O10: 4.81 | P10: 75 | Q10: 27862 | R10: 113364 | S10: 4845 | T10: 1.03
A11: 10 | B11: Phase 1 | C11: 80102 | D11: 961225 | E11: 0.15 | F11: 77 | G11: 10 | H11: 0.05 | I11: 1040 | J11: 4535 | K11: 249669 | L11: 55.1x | M11: 0.6 | N11: 33262 | O11: 3.18 | P11: 75 | Q11: 32041 | R11: 113364 | S11: 5572 | T11: 1.03
A12: 11 | B12: Phase 1 | C12: 92117 | D12: 1105408 | E12: 0.15 | F12: 88 | G12: 11 | H12: 0.05 | I12: 1047 | J12: 4122 | K12: 251229 | L12: 60.9x | M12: 0.6 | N12: 21247 | O12: 1.77 | P12: 75 | Q12: 36847 | R12: 113364 | S12: 6408 | T12: 1.03
A13: 12 | B13: Phase 1 | C13: 105935 | D13: 1271219 | E13: 0.15 | F13: 101 | G13: 13 | H13: 0.05 | I13: 1049 | J13: 3488 | K13: 251727 | L13: 72.2x | M13: 0.6 | N13: 7429 | O13: 0.54 | P13: 75 | Q13: 42374 | R13: 113364 | S13: 7369 | T13: 1.03
A14: 13 | B14: Phase 2 | C14: 121825 | D14: 1461902 | E14: 0.15 | F14: 116 | G14: 15 | H14: 0.05 | I14: 1050 | J14: 3023 | K14: 252052 | L14: 83.4x | M14: 0.6 | N14: -8461 | O14: -0.53 | P14: 75 | Q14: 48730 | R14: 113364 | S14: 8475 | T14: 1.03
... A37: 36 | B37: Phase 4 | C37: 3032407 | D37: 36388880 | E37: 0.15 | F37: 2799 | G37: 365 | H37: 0.05 | I37: 1083 | J37: 124 | K37: 260013 | L37: 2092.9x | M37: 0.6 | N37: -2919042 | O37: -7.38 | P37: 75 | Q37: 1212963 | R37: 113364 | S37: 210950 | T37: 1.03

Sheet Sheet2
A1: ='Financial Model'!H1 -> Month to Month Account Growth | B1: ='Financial Model'!I1 -> 1 | C1: ='Financial Model'!J1 -> 1 | D1: ='Financial Model'!K1 -> 1.5 | E1: ='Financial Model'!L1 -> 1.1 | F1: ='Financial Model'!M1 -> 1.15 | G1: ='Financial Model'!N1 -> 1.15 | H1: ='Financial Model'!O1 -> 1.2 | ... U1: ='Financial Model'!AB1 -> 1.15
A2: ='Financial Model'!H2 -> Contract Account Growth | B2: ='Financial Model'!I2 -> 1 | C2: ='Financial Model'!J2 -> 2 | D2: ='Financial Model'!K2 -> 2 | E2: ='Financial Model'!L2 -> 0.6 | F2: ='Financial Model'!M2 -> 1.15 | G2: ='Financial Model'!N2 -> 1.15 | H2: ='Financial Model'!O2 -> 1.2 | ... U2: ='Financial Model'!AB2 -> 1.15
A3: ='Financial Model'!H3 -> 0 | B3: ='Financial Model'!I3 -> 0 | C3: ='Financial Model'!J3 -> 0 | D3: ='Financial Model'!K3 -> 0 | E3: ='Financial Model'!L3 -> 0 | F3: ='Financial Model'!M3 -> 0 | G3: ='Financial Model'!N3 -> 0 | H3: ='Financial Model'!O3 -> 0 | ... U3: ='Financial Model'!AB3 -> 0
A4: ='Financial Model'!H4 -> 0 | B4: ='Financial Model'!I4 -> 0 | C4: ='Financial Model'!J4 -> 0 | D4: ='Financial Model'!K4 -> 0 | E4: ='Financial Model'!L4 -> 0 | F4: ='Financial Model'!M4 -> 0 | G4: ='Financial Model'!N4 -> 0 | H4: ='Financial Model'!O4 -> 0 | ... U4: ='Financial Model'!AB4 -> 0
A5: ='Financial Model'!H5 -> 0 | B5: ='Financial Model'!I5 -> Jan | C5: ='Financial Model'!J5 -> 0 | D5: ='Financial Model'!K5 -> 0 | E5: ='Financial Model'!L5 -> 0 | F5: ='Financial Model'!M5 -> 0 | G5: ='Financial Model'!N5 -> 0 | H5: ='Financial Model'!O5 -> 0 | ... U5: ='Financial Model'!AB5 -> 0
A6: ` | B6: ='Financial Model'!I6 -> Month 1 | C6: ='Financial Model'!J6 -> Month 2 | D6: ='Financial Model'!K6 -> Month 3 | E6: ='Financial Model'!L6 -> Month 4 | F6: ='Financial Model'!M6 -> Month 5 | G6: ='Financial Model'!N6 -> Month 6 | H6: ='Financial Model'!O6 -> Month 7 | I6: ='Financial Model'!P6 -> Month 8 | ... U6: ='Financial Model'!AB6 -> Month 20
A7: ='Financial Model'!H7 -> Total Customer Count | B7: ='Financial Model'!I7 -> 18 | C7: ='Financial Model'!J7 -> 20.65 | D7: ='Financial Model'!K7 -> 26.0175 | E7: ='Financial Model'!L7 -> 29.366625 | F7: ='Financial Model'!M7 -> 33.598294 | G7: ='Financial Model'!N7 -> 38.473379 | H7: ='Financial Model'!O7 -> 44.464873 | ... U7: ='Financial Model'!AB7 -> 441.82827
A8: ='Financial Model'!H8 -> Total Recurring Monthly Revenue | B8: ='Financial Model'!I8 -> 13800 | C8: ='Financial Model'!J8 -> 23765 | D8: ='Financial Model'!K8 -> 43386.242 | E8: ='Financial Model'!L8 -> 53119.271 | F8: ='Financial Model'!M8 -> 64621.847 | G8: ='Financial Model'!N8 -> 77564.822 | H8: ='Financial Model'!O8 -> 93090.439 | ... U8: ='Financial Model'!AB8 -> 1059050.8
A9: ='Financial Model'!H9 -> Total Revenue Collected | B9: ='Financial Model'!I9 -> 13800 | C9: ='Financial Model'!J9 -> 23765 | D9: ='Financial Model'!K9 -> 43386.242 | E9: ='Financial Model'!L9 -> 53119.271 | F9: ='Financial Model'!M9 -> 64621.847 | G9: ='Financial Model'!N9 -> 77564.822 | H9: ='Financial Model'!O9 -> 93090.439 | ... U9: ='Financial Model'!AB9 -> 1059050.8
A10: ='Financial Model'!H10 -> COGS | B10: ='Financial Model'!I10 -> -13755.92 | C10: ='Financial Model'!J10 -> -13993.545 | D10: ='Financial Model'!K10 -> -16362.575 | E10: ='Financial Model'!L10 -> -17249.869 | F10: ='Financial Model'!M10 -> -18557.87 | G10: ='Financial Model'!N10 -> -20030.084 | H10: ='Financial Model'!O10 -> -22154.147 | ... U10: ='Financial Model'!AB10 -> -132492.15
A11: ='Financial Model'!H12 -> Working Capital | B11: ='Financial Model'!I12 -> 0 | C11: ='Financial Model'!J12 -> -107598.59 | D11: ='Financial Model'!K12 -> -21503.518 | E11: ='Financial Model'!L12 -> 355583.88 | F11: ='Financial Model'!M12 -> 300816.98 | G11: ='Financial Model'!N12 -> 251314.16 | H11: ='Financial Model'!O12 -> 193526.44 | ... U11: ='Financial Model'!AB12 -> 885699.75
A12: ='Financial Model'!H13 -> Capital Raise | B12: ='Financial Model'!I13 -> 0 | C12: ='Financial Model'!J13 -> 215000 | D12: ='Financial Model'!K13 -> 500000 | E12: ='Financial Model'!L13 -> 60000 | F12: ='Financial Model'!M13 -> 60000 | G12: ='Financial Model'!N13 -> 115000 | H12: ='Financial Model'!O13 -> 150000 | ... U12: ='Financial Model'!AB13 -> 0
A13: ='Financial Model'!H14 -> Inhouse Capital Requirement | B13: ='Financial Model'!I14 -> -107598.59 | C13: ='Financial Model'!J14 -> -21503.518 | D13: ='Financial Model'!K14 -> 355583.88 | E13: ='Financial Model'!L14 -> 300816.98 | F13: ='Financial Model'!M14 -> 251314.16 | G13: ='Financial Model'!N14 -> 193526.44 | H13: ='Financial Model'!O14 -> 140781.07 | ... U13: ='Financial Model'!AB14 -> 1172974.4
A14: ='Financial Model'!H15 -> Total Creation Multiple | B14: ='Financial Model'!I15 -> 0 | C14: ='Financial Model'!J15 -> 0 | D14: ='Financial Model'!K15 -> 0 | E14: ='Financial Model'!L15 -> 0 | F14: ='Financial Model'!M15 -> 0 | G14: ='Financial Model'!N15 -> 0 | H14: ='Financial Model'!O15 -> 0 | ... U14: ='Financial Model'!AB15 -> 0
A15: ='Financial Model'!H16 -> Revenue Summary | B15: ='Financial Model'!I16 -> 1 | C15: ='Financial Model'!J16 -> 2 | D15: ='Financial Model'!K16 -> 3 | E15: ='Financial Model'!L16 -> 4 | F15: ='Financial Model'!M16 -> 5 | G15: ='Financial Model'!N16 -> 6 | H15: ='Financial Model'!O16 -> 7 | ... U15: ='Financial Model'!AB16 -> 20
A16: ='Financial Model'!H17 -> Total Accounts | B16: ='Financial Model'!I17 -> 15 | C16: ='Financial Model'!J17 -> 16.65 | D16: ='Financial Model'!K17 -> 19.0175 | E16: ='Financial Model'!L17 -> 23.666625 | F16: ='Financial Model'!M17 -> 27.043294 | G16: ='Financial Model'!N17 -> 30.935129 | H16: ='Financial Model'!O17 -> 35.418973 | ... U16: ='Financial Model'!AB17 -> 346.94563
A17: ='Financial Model'!H18 -> Montly Accounts Sold | B17: ='Financial Model'!I18 -> 2 | C17: ='Financial Model'!J18 -> 2 | D17: ='Financial Model'!K18 -> 3 | E17: ='Financial Model'!L18 -> 3.3 | F17: ='Financial Model'!M18 -> 3.795 | G17: ='Financial Model'!N18 -> 4.36425 | H17: ='Financial Model'!O18 -> 5.2371 | ... U17: ='Financial Model'!AB18 -> 55.186513
A18: ='Financial Model'!H19 -> Contract Account Sold | B18: ='Financial Model'!I19 -> 1 | C18: ='Financial Model'!J19 -> 2 | D18: ='Financial Model'!K19 -> 4 | E18: ='Financial Model'!L19 -> 2.4 | F18: ='Financial Model'!M19 -> 2.76 | G18: ='Financial Model'!N19 -> 3.174 | H18: ='Financial Model'!O19 -> 3.8088 | ... U18: ='Financial Model'!AB19 -> 39.696126
A19: ='Financial Model'!H20 -> Total Paid Accounts Onboarded | B19: ='Financial Model'!I20 -> 3 | C19: ='Financial Model'!J20 -> 4 | D19: ='Financial Model'!K20 -> 7 | E19: ='Financial Model'!L20 -> 5.7 | F19: ='Financial Model'!M20 -> 6.555 | G19: ='Financial Model'!N20 -> 7.53825 | H19: ='Financial Model'!O20 -> 9.0459 | ... U19: ='Financial Model'!AB20 -> 94.882638
A20: ='Financial Model'!H21 -> Average MMR | B20: ='Financial Model'!I21 -> 520 | C20: ='Financial Model'!J21 -> 766.66667 | D20: ='Financial Model'!K21 -> 1150.8475 | E20: ='Financial Model'!L21 -> 1667.5792 | F20: ='Financial Model'!M21 -> 1808.8313 | G20: ='Financial Model'!N21 -> 1923.3669 | H20: ='Financial Model'!O21 -> 2016.0647 | ... U20: ='Financial Model'!AB21 -> 2398.182
A21: ='Financial Model'!H22 -> New Month-to-Month Average | B21: ='Financial Model'!I22 -> 500 | C21: ='Financial Model'!J22 -> 500 | D21: ='Financial Model'!K22 -> 500 | E21: ='Financial Model'!L22 -> 501 | F21: ='Financial Model'!M22 -> 502 | G21: ='Financial Model'!N22 -> 503 | H21: ='Financial Model'!O22 -> 504 | ... U21: ='Financial Model'!AB22 -> 517
A22: ='Financial Model'!H23 -> New Contract Average | B22: ='Financial Model'!I23 -> 5000 | C22: ='Financial Model'!J23 -> 5000 | D22: ='Financial Model'!K23 -> 5000 | E22: ='Financial Model'!L23 -> 5000 | F22: ='Financial Model'!M23 -> 5000 | G22: ='Financial Model'!N23 -> 5000 | H22: ='Financial Model'!O23 -> 5000 | ... U22: ='Financial Model'!AB23 -> 5000
... A26: ='Financial Model'!H27 -> Total Monthly Revenue | B26: ='Financial Model'!I27 -> 13800 | C26: ='Financial Model'!J27 -> 23765 | D26: ='Financial Model'!K27 -> 43386.242 | E26: ='Financial Model'!L27 -> 53119.271 | F26: ='Financial Model'!M27 -> 64621.847 | G26: ='Financial Model'!N27 -> 77564.822 | H26: ='Financial Model'!O27 -> 93090.439 | ... U26: ='Financial Model'!AB27 -> 1059050.8
A27: ='Financial Model'!#REF! -> #REF! | B27: ='Financial Model'!#REF! -> #REF! | C27: ='Financial Model'!#REF! -> #REF! | D27: ='Financial Model'!#REF! -> #REF! | E27: ='Financial Model'!#REF! -> #REF! | F27: ='Financial Model'!#REF! -> #REF! | G27: ='Financial Model'!#REF! -> #REF! | H27: ='Financial Model'!#REF! -> #REF! | ... U27: ='Financial Model'!#REF! -> #REF!
A28: ='Financial Model'!H28 -> 0 | B28: ='Financial Model'!I28 -> 0 | C28: ='Financial Model'!J28 -> 0 | D28: ='Financial Model'!K28 -> 0 | E28: ='Financial Model'!L28 -> 0 | F28: ='Financial Model'!M28 -> 0 | G28: ='Financial Model'!N28 -> 0 | H28: ='Financial Model'!O28 -> 0 | ... U28: ='Financial Model'!AB28 -> 0
A29: ='Financial Model'!H29 -> Gross Profit | B29: ='Financial Model'!I29 -> 44.08 | C29: ='Financial Model'!J29 -> 9771.4553 | D29: ='Financial Model'!K29 -> 27023.666 | E29: ='Financial Model'!L29 -> 35869.402 | F29: ='Financial Model'!M29 -> 46063.977 | G29: ='Financial Model'!N29 -> 57534.737 | H29: ='Financial Model'!O29 -> 70936.292 | ... U29: ='Financial Model'!AB29 -> 926558.68
A30: ='Financial Model'!H30 -> 0 | B30: ='Financial Model'!I30 -> 0 | C30: ='Financial Model'!J30 -> 0 | D30: ='Financial Model'!K30 -> 0 | E30: ='Financial Model'!L30 -> 0 | F30: ='Financial Model'!M30 -> 0 | G30: ='Financial Model'!N30 -> 0 | H30: ='Financial Model'!O30 -> 0 | ... U30: ='Financial Model'!AB30 -> 0
A31: ='Financial Model'!H31 -> COGS | B31: ='Financial Model'!I31 -> 0 | C31: ='Financial Model'!J31 -> 0 | D31: ='Financial Model'!K31 -> 0 | E31: ='Financial Model'!L31 -> 0 | F31: ='Financial Model'!M31 -> 0 | G31: ='Financial Model'!N31 -> 0 | H31: ='Financial Model'!O31 -> 0 | ... U31: ='Financial Model'!AB31 -> 0
A32: ='Financial Model'!#REF! -> #REF! | B32: ='Financial Model'!#REF! -> #REF! | C32: ='Financial Model'!#REF! -> #REF! | D32: ='Financial Model'!#REF! -> #REF! | E32: ='Financial Model'!#REF! -> #REF! | F32: ='Financial Model'!#REF! -> #REF! | G32: ='Financial Model'!#REF! -> #REF! | H32: ='Financial Model'!#REF! -> #REF! | ... U32: ='Financial Model'!#REF! -> #REF!
A33: ='Financial Model'!#REF! -> #REF! | B33: ='Financial Model'!#REF! -> #REF! | C33: ='Financial Model'!#REF! -> #REF! | D33: ='Financial Model'!#REF! -> #REF! | E33: ='Financial Model'!#REF! -> #REF! | F33: ='Financial Model'!#REF! -> #REF! | G33: ='Financial Model'!#REF! -> #REF! | H33: ='Financial Model'!#REF! -> #REF! | ... U33: ='Financial Model'!#REF! -> #REF!
A34: ='Financial Model'!#REF! -> #REF! | B34: ='Financial Model'!#REF! -> #REF! | C34: ='Financial Model'!#REF! -> #REF! | D34: ='Financial Model'!#REF! -> #REF! | E34: ='Financial Model'!#REF! -> #REF! | F34: ='Financial Model'!#REF! -> #REF! | G34: ='Financial Model'!#REF! -> #REF! | H34: ='Financial Model'!#REF! -> #REF! | ... U34: ='Financial Model'!#REF! -> #REF!
A35: ='Financial Model'!#REF! -> #REF! | B35: ='Financial Model'!#REF! -> #REF! | C35: ='Financial Model'!#REF! -> #REF! | D35: ='Financial Model'!#REF! -> #REF! | E35: ='Financial Model'!#REF! -> #REF! | F35: ='Financial Model'!#REF! -> #REF! | G35: ='Financial Model'!#REF! -> #REF! | H35: ='Financial Model'!#REF! -> #REF! | ... U35: ='Financial Model'!#REF! -> #REF!
A36: ='Financial Model'!#REF! -> #REF! | B36: ='Financial Model'!#REF! -> #REF! | C36: ='Financial Model'!#REF! -> #REF! | D36: ='Financial Model'!#REF! -> #REF! | E36: ='Financial Model'!#REF! -> #REF! | F36: ='Financial Model'!#REF! -> #REF! | G36: ='Financial Model'!#REF! -> #REF! | H36: ='Financial Model'!#REF! -> #REF! | ... U36: ='Financial Model'!#REF! -> #REF!
A37: ='Financial Model'!#REF! -> #REF! | B37: ='Financial Model'!#REF! -> #REF! | C37: ='Financial Model'!#REF! -> #REF! | D37: ='Financial Model'!#REF! -> #REF! | E37: ='Financial Model'!#REF! -> #REF! | F37: ='Financial Model'!#REF! -> #REF! | G37: ='Financial Model'!#REF! -> #REF! | H37: ='Financial Model'!#REF! -> #REF! | ... U37: ='Financial Model'!#REF! -> #REF!
A38: ='Financial Model'!#REF! -> #REF! | B38: ='Financial Model'!#REF! -> #REF! | C38: ='Financial Model'!#REF! -> #REF! | D38: ='Financial Model'!#REF! -> #REF! | E38: ='Financial Model'!#REF! -> #REF! | F38: ='Financial Model'!#REF! -> #REF! | G38: ='Financial Model'!#REF! -> #REF! | H38: ='Financial Model'!#REF! -> #REF! | ... U38: ='Financial Model'!#REF! -> #REF!
A39: ='Financial Model'!#REF! -> #REF! | B39: ='Financial Model'!#REF! -> #REF! | C39: ='Financial Model'!#REF! -> #REF! | D39: ='Financial Model'!#REF! -> #REF! | E39: ='Financial Model'!#REF! -> #REF! | F39: ='Financial Model'!#REF! -> #REF! | G39: ='Financial Model'!#REF! -> #REF! | H39: ='Financial Model'!#REF! -> #REF! | ... U39: ='Financial Model'!#REF! -> #REF!
A40: ='Financial Model'!#REF! -> #REF! | B40: ='Financial Model'!#REF! -> #REF! | C40: ='Financial Model'!#REF! -> #REF! | D40: ='Financial Model'!#REF! -> #REF! | E40: ='Financial Model'!#REF! -> #REF! | F40: ='Financial Model'!#REF! -> #REF! | G40: ='Financial Model'!#REF! -> #REF! | H40: ='Financial Model'!#REF! -> #REF! | ... U40: ='Financial Model'!#REF! -> #REF!
A41: ='Financial Model'!#REF! -> #REF! | B41: ='Financial Model'!#REF! -> #REF! | C41: ='Financial Model'!#REF! -> #REF! | D41: ='Financial Model'!#REF! -> #REF! | E41: ='Financial Model'!#REF! -> #REF! | F41: ='Financial Model'!#REF! -> #REF! | G41: ='Financial Model'!#REF! -> #REF! | H41: ='Financial Model'!#REF! -> #REF! | ... U41: ='Financial Model'!#REF! -> #REF!
A42: ='Financial Model'!#REF! -> #REF! | B42: ='Financial Model'!#REF! -> #REF! | C42: ='Financial Model'!#REF! -> #REF! | D42: ='Financial Model'!#REF! -> #REF! | E42: ='Financial Model'!#REF! -> #REF! | F42: ='Financial Model'!#REF! -> #REF! | G42: ='Financial Model'!#REF! -> #REF! | H42: ='Financial Model'!#REF! -> #REF! | ... U42: ='Financial Model'!#REF! -> #REF!
A43: ='Financial Model'!#REF! -> #REF! | B43: ='Financial Model'!#REF! -> #REF! | C43: ='Financial Model'!#REF! -> #REF! | D43: ='Financial Model'!#REF! -> #REF! | E43: ='Financial Model'!#REF! -> #REF! | F43: ='Financial Model'!#REF! -> #REF! | G43: ='Financial Model'!#REF! -> #REF! | H43: ='Financial Model'!#REF! -> #REF! | ... U43: ='Financial Model'!#REF! -> #REF!
A44: ='Financial Model'!#REF! -> #REF! | B44: ='Financial Model'!#REF! -> #REF! | C44: ='Financial Model'!#REF! -> #REF! | D44: ='Financial Model'!#REF! -> #REF! | E44: ='Financial Model'!#REF! -> #REF! | F44: ='Financial Model'!#REF! -> #REF! | G44: ='Financial Model'!#REF! -> #REF! | H44: ='Financial Model'!#REF! -> #REF! | ... U44: ='Financial Model'!#REF! -> #REF!
A45: ='Financial Model'!H37 -> Total COGS | B45: ='Financial Model'!I37 -> -13755.92 | C45: ='Financial Model'!J37 -> -13993.545 | D45: ='Financial Model'!K37 -> -16362.575 | E45: ='Financial Model'!L37 -> -17249.869 | F45: ='Financial Model'!M37 -> -18557.87 | G45: ='Financial Model'!N37 -> -20030.084 | H45: ='Financial Model'!O37 -> -22154.147 | ... U45: ='Financial Model'!AB37 -> -132492.15
A46: ='Financial Model'!#REF! -> #REF! | B46: ='Financial Model'!#REF! -> #REF! | C46: ='Financial Model'!#REF! -> #REF! | D46: ='Financial Model'!#REF! -> #REF! | E46: ='Financial Model'!#REF! -> #REF! | F46: ='Financial Model'!#REF! -> #REF! | G46: ='Financial Model'!#REF! -> #REF! | H46: ='Financial Model'!#REF! -> #REF! | ... U46: ='Financial Model'!#REF! -> #REF!
A47: ='Financial Model'!#REF! -> #REF! | B47: ='Financial Model'!#REF! -> #REF! | C47: ='Financial Model'!#REF! -> #REF! | D47: ='Financial Model'!#REF! -> #REF! | E47: ='Financial Model'!#REF! -> #REF! | F47: ='Financial Model'!#REF! -> #REF! | G47: ='Financial Model'!#REF! -> #REF! | H47: ='Financial Model'!#REF! -> #REF! | ... U47: ='Financial Model'!#REF! -> #REF!
A48: ='Financial Model'!#REF! -> #REF! | B48: ='Financial Model'!#REF! -> #REF! | C48: ='Financial Model'!#REF! -> #REF! | D48: ='Financial Model'!#REF! -> #REF! | E48: ='Financial Model'!#REF! -> #REF! | F48: ='Financial Model'!#REF! -> #REF! | G48: ='Financial Model'!#REF! -> #REF! | H48: ='Financial Model'!#REF! -> #REF! | ... U48: ='Financial Model'!#REF! -> #REF!
A49: ='Financial Model'!#REF! -> #REF! | B49: ='Financial Model'!#REF! -> #REF! | C49: ='Financial Model'!#REF! -> #REF! | D49: ='Financial Model'!#REF! -> #REF! | E49: ='Financial Model'!#REF! -> #REF! | F49: ='Financial Model'!#REF! -> #REF! | G49: ='Financial Model'!#REF! -> #REF! | H49: ='Financial Model'!#REF! -> #REF! | ... U49: ='Financial Model'!#REF! -> #REF!
A50: ='Financial Model'!#REF! -> #REF! | B50: ='Financial Model'!#REF! -> #REF! | C50: ='Financial Model'!#REF! -> #REF! | D50: ='Financial Model'!#REF! -> #REF! | E50: ='Financial Model'!#REF! -> #REF! | F50: ='Financial Model'!#REF! -> #REF! | G50: ='Financial Model'!#REF! -> #REF! | H50: ='Financial Model'!#REF! -> #REF! | ... U50: ='Financial Model'!#REF! -> #REF!
A51: ='Financial Model'!#REF! -> #REF! | B51: ='Financial Model'!#REF! -> #REF! | C51: ='Financial Model'!#REF! -> #REF! | D51: ='Financial Model'!#REF! -> #REF! | E51: ='Financial Model'!#REF! -> #REF! | F51: ='Financial Model'!#REF! -> #REF! | G51: ='Financial Model'!#REF! -> #REF! | H51: ='Financial Model'!#REF! -> #REF! | ... U51: ='Financial Model'!#REF! -> #REF!
A52: ='Financial Model'!#REF! -> #REF! | B52: ='Financial Model'!#REF! -> #REF! | C52: ='Financial Model'!#REF! -> #REF! | D52: ='Financial Model'!#REF! -> #REF! | E52: ='Financial Model'!#REF! -> #REF! | F52: ='Financial Model'!#REF! -> #REF! | G52: ='Financial Model'!#REF! -> #REF! | H52: ='Financial Model'!#REF! -> #REF! | ... U52: ='Financial Model'!#REF! -> #REF!
A53: ='Financial Model'!#REF! -> #REF! | B53: ='Financial Model'!#REF! -> #REF! | C53: ='Financial Model'!#REF! -> #REF! | D53: ='Financial Model'!#REF! -> #REF! | E53: ='Financial Model'!#REF! -> #REF! | F53: ='Financial Model'!#REF! -> #REF! | G53: ='Financial Model'!#REF! -> #REF! | H53: ='Financial Model'!#REF! -> #REF! | ... U53: ='Financial Model'!#REF! -> #REF!
A54: ='Financial Model'!H39 -> 0 | B54: ='Financial Model'!I39 -> 0 | C54: ='Financial Model'!J39 -> 0 | D54: ='Financial Model'!K39 -> 0 | E54: ='Financial Model'!L39 -> 0 | F54: ='Financial Model'!M39 -> 0 | G54: ='Financial Model'!N39 -> 0 | H54: ='Financial Model'!O39 -> 0 | ... U54: ='Financial Model'!AB39 -> 0
A55: ='Financial Model'!H40 -> Operating Costs | B55: ='Financial Model'!I40 -> 0 | C55: ='Financial Model'!J40 -> 0 | D55: ='Financial Model'!K40 -> 0 | E55: ='Financial Model'!L40 -> 0 | F55: ='Financial Model'!M40 -> 0 | G55: ='Financial Model'!N40 -> 0 | H55: ='Financial Model'!O40 -> 0 | ... U55: ='Financial Model'!AB40 -> 0
A56: ='Financial Model'!H41 -> Bank Service Charges | B56: ='Financial Model'!I41 -> -250 | C56: ='Financial Model'!J41 -> -250 | D56: ='Financial Model'!K41 -> -250 | E56: ='Financial Model'!L41 -> -250 | F56: ='Financial Model'!M41 -> -250 | G56: ='Financial Model'!N41 -> -250 | H56: ='Financial Model'!O41 -> -250 | ... U56: ='Financial Model'!AB41 -> -250
A57: ='Financial Model'!H42 -> Total Contract labor | B57: ='Financial Model'!I42 -> -67256.133 | C57: ='Financial Model'!J42 -> -70618.94 | D57: ='Financial Model'!K42 -> -74149.887 | E57: ='Financial Model'!L42 -> -77857.381 | F57: ='Financial Model'!M42 -> -85643.119 | G57: ='Financial Model'!N42 -> -94207.431 | H57: ='Financial Model'!O42 -> -103628.17 | ... U57: ='Financial Model'!AB42 -> -160683.37
A58: ='Financial Model'!H43 -> Lincense and Subscription Fees | B58: ='Financial Model'!I43 -> -121.36364 | C58: ='Financial Model'!J43 -> -124.39773 | D58: ='Financial Model'!K43 -> -127.50767 | E58: ='Financial Model'!L43 -> -130.69536 | F58: ='Financial Model'!M43 -> -133.96275 | G58: ='Financial Model'!N43 -> -137.31181 | H58: ='Financial Model'!O43 -> -140.74461 | ... U58: ='Financial Model'!AB43 -> -194.018
A59: ='Financial Model'!H55 -> Health Insurance Expense | B59: ='Financial Model'!I55 -> 0 | C59: ='Financial Model'!J55 -> 0 | D59: ='Financial Model'!K55 -> 0 | E59: ='Financial Model'!L55 -> 0 | F59: ='Financial Model'!M55 -> 0 | G59: ='Financial Model'!N55 -> 3 | H59: ='Financial Model'!O55 -> -13303.198 | ... U59: ='Financial Model'!AB55 -> -15572.575
A60: ='Financial Model'!H56 -> Work Comp and Liability Insurance | B60: ='Financial Model'!I56 -> 0 | C60: ='Financial Model'!J56 -> 0 | D60: ='Financial Model'!K56 -> 0 | E60: ='Financial Model'!L56 -> 0 | F60: ='Financial Model'!M56 -> 0 | G60: ='Financial Model'!N56 -> -2563.005 | H60: ='Financial Model'!O56 -> -3075.606 | ... U60: ='Financial Model'!AB56 -> -32260.097
A61: ='Financial Model'!#REF! -> #REF! | B61: ='Financial Model'!#REF! -> #REF! | C61: ='Financial Model'!#REF! -> #REF! | D61: ='Financial Model'!#REF! -> #REF! | E61: ='Financial Model'!#REF! -> #REF! | F61: ='Financial Model'!#REF! -> #REF! | G61: ='Financial Model'!#REF! -> #REF! | H61: ='Financial Model'!#REF! -> #REF! | ... U61: ='Financial Model'!#REF! -> #REF!
A62: ='Financial Model'!H57 -> Meals and Entertainment | B62: ='Financial Model'!I57 -> -1000 | C62: ='Financial Model'!J57 -> -1050 | D62: ='Financial Model'!K57 -> -1155 | E62: ='Financial Model'!L57 -> -1270.5 | F62: ='Financial Model'!M57 -> -1397.55 | G62: ='Financial Model'!N57 -> -1537.305 | H62: ='Financial Model'!O57 -> -1691.0355 | ... U62: ='Financial Model'!AB57 -> -3318.2345
A63: ='Financial Model'!H58 -> Office Supplies | B63: ='Financial Model'!I58 -> 0 | C63: ='Financial Model'!J58 -> 0 | D63: ='Financial Model'!K58 -> 0 | E63: ='Financial Model'!L58 -> 0 | F63: ='Financial Model'!M58 -> 250 | G63: ='Financial Model'!N58 -> 250 | H63: ='Financial Model'!O58 -> 250 | ... U63: ='Financial Model'!AB58 -> 250
A64: ='Financial Model'!#REF! -> #REF! | B64: ='Financial Model'!#REF! -> #REF! | C64: ='Financial Model'!#REF! -> #REF! | D64: ='Financial Model'!#REF! -> #REF! | E64: ='Financial Model'!#REF! -> #REF! | F64: ='Financial Model'!#REF! -> #REF! | G64: ='Financial Model'!#REF! -> #REF! | H64: ='Financial Model'!#REF! -> #REF! | ... U64: ='Financial Model'!#REF! -> #REF!
A65: ='Financial Model'!#REF! -> #REF! | B65: ='Financial Model'!#REF! -> #REF! | C65: ='Financial Model'!#REF! -> #REF! | D65: ='Financial Model'!#REF! -> #REF! | E65: ='Financial Model'!#REF! -> #REF! | F65: ='Financial Model'!#REF! -> #REF! | G65: ='Financial Model'!#REF! -> #REF! | H65: ='Financial Model'!#REF! -> #REF! | ... U65: ='Financial Model'!#REF! -> #REF!
A66: ='Financial Model'!H59 -> Rent Expense | B66: ='Financial Model'!I59 -> 0 | C66: ='Financial Model'!J59 -> 0 | D66: ='Financial Model'!K59 -> 0 | E66: ='Financial Model'!L59 -> 0 | F66: ='Financial Model'!M59 -> 5000 | G66: ='Financial Model'!N59 -> 5000 | H66: ='Financial Model'!O59 -> 5000 | ... U66: ='Financial Model'!AB59 -> 5000
A67: ='Financial Model'!#REF! -> #REF! | B67: ='Financial Model'!#REF! -> #REF! | C67: ='Financial Model'!#REF! -> #REF! | D67: ='Financial Model'!#REF! -> #REF! | E67: ='Financial Model'!#REF! -> #REF! | F67: ='Financial Model'!#REF! -> #REF! | G67: ='Financial Model'!#REF! -> #REF! | H67: ='Financial Model'!#REF! -> #REF! | ... U67: ='Financial Model'!#REF! -> #REF!
A68: ='Financial Model'!#REF! -> #REF! | B68: ='Financial Model'!#REF! -> #REF! | C68: ='Financial Model'!#REF! -> #REF! | D68: ='Financial Model'!#REF! -> #REF! | E68: ='Financial Model'!#REF! -> #REF! | F68: ='Financial Model'!#REF! -> #REF! | G68: ='Financial Model'!#REF! -> #REF! | H68: ='Financial Model'!#REF! -> #REF! | ... U68: ='Financial Model'!#REF! -> #REF!
A69: ='Financial Model'!H60 -> 0 | B69: ='Financial Model'!I60 -> 0 | C69: ='Financial Model'!J60 -> 0 | D69: ='Financial Model'!K60 -> 0 | E69: ='Financial Model'!L60 -> 0 | F69: ='Financial Model'!M60 -> 0 | G69: ='Financial Model'!N60 -> 0 | H69: ='Financial Model'!O60 -> 0 | ... U69: ='Financial Model'!AB60 -> 0
A70: ='Financial Model'!H61 -> Total Operating Costs | B70: ='Financial Model'!I61 -> -107642.67 | C70: ='Financial Model'!J61 -> -138676.39 | D70: ='Financial Model'!K61 -> -149936.27 | E70: ='Financial Model'!L61 -> -150636.3 | F70: ='Financial Model'!M61 -> -155566.8 | G70: ='Financial Model'!N61 -> -230322.46 | H70: ='Financial Model'!O61 -> -273681.66 | ... U70: ='Financial Model'!AB61 -> -639284.01
A71: ='Financial Model'!#REF! -> #REF! | B71: ='Financial Model'!I72 -> 1 | C71: ='Financial Model'!J72 -> 1 | D71: ='Financial Model'!K72 -> 1 | E71: ='Financial Model'!L72 -> 1 | F71: ='Financial Model'!M72 -> 1 | G71: ='Financial Model'!N72 -> 1 | H71: ='Financial Model'!O72 -> 1 | I71: ='Financial Model'!P72 -> 1 | ... U71: ='Financial Model'!AB72 -> 1
A72: ='Financial Model'!#REF! -> #REF! | B72: ='Financial Model'!I73 -> 1.25 | C72: ='Financial Model'!J73 -> 1.05 | D72: ='Financial Model'!K73 -> 1.05 | E72: ='Financial Model'!L73 -> 1.05 | F72: ='Financial Model'!M73 -> 1.1 | G72: ='Financial Model'!N73 -> 1.1 | H72: ='Financial Model'!O73 -> 1.1 | I72: ='Financial Model'!P73 -> 1.1 | ... U72: ='Financial Model'!AB73 -> 1.025
A73: ='Financial Model'!#REF! -> #REF! | B73: ='Financial Model'!I74 -> 1 | C73: ='Financial Model'!J74 -> 1.025 | D73: ='Financial Model'!K74 -> 1.025 | E73: ='Financial Model'!L74 -> 1.025 | F73: ='Financial Model'!M74 -> 1.025 | G73: ='Financial Model'!N74 -> 1.025 | H73: ='Financial Model'!O74 -> 1.025 | I73: ='Financial Model'!P74 -> 1.025 | ... U73: ='Financial Model'!AB74 -> 1.025
A74: ='Financial Model'!H72 -> Bank Service Charges | B74: ='Financial Model'!I82 -> 0 | C74: ='Financial Model'!J82 -> 0 | D74: ='Financial Model'!K82 -> 0 | E74: ='Financial Model'!L82 -> 0 | F74: ='Financial Model'!M82 -> 0 | G74: ='Financial Model'!N82 -> 3 | H74: ='Financial Model'!O82 -> -13303.198 | I74: ='Financial Model'!P82 -> -14142.069 | ... U74: ='Financial Model'!AB82 -> -15572.575
A75: ='Financial Model'!H73 -> Total Contract labor | B75: ='Financial Model'!I83 -> 0 | C75: ='Financial Model'!J83 -> 0 | D75: ='Financial Model'!K83 -> 0 | E75: ='Financial Model'!L83 -> 0 | F75: ='Financial Model'!M83 -> 0 | G75: ='Financial Model'!N83 -> 0 | H75: ='Financial Model'!O83 -> 0 | I75: ='Financial Model'!P83 -> 0 | ... U75: ='Financial Model'!AB83 -> 0
A76: ='Financial Model'!H74 -> Lincense and Subscription Fees | B76: ='Financial Model'!I84 -> 1 | C76: ='Financial Model'!J84 -> 1 | D76: ='Financial Model'!K84 -> 1 | E76: ='Financial Model'!L84 -> 1 | F76: ='Financial Model'!M84 -> 1 | G76: ='Financial Model'!N84 -> 1 | H76: ='Financial Model'!O84 -> 1 | I76: ='Financial Model'!P84 -> 1 | ... U76: ='Financial Model'!AB84 -> 1
A77: ='Financial Model'!H82 -> Health Insurance Expense | B77: ='Financial Model'!I85 -> 2 | C77: ='Financial Model'!J85 -> 1.05 | D77: ='Financial Model'!K85 -> 1.1 | E77: ='Financial Model'!L85 -> 1.1 | F77: ='Financial Model'!M85 -> 1.1 | G77: ='Financial Model'!N85 -> 1.1 | H77: ='Financial Model'!O85 -> 1.1 | I77: ='Financial Model'!P85 -> 1.1 | ... U77: ='Financial Model'!AB85 -> 1.025
A78: ='Financial Model'!H83 -> Work Comp and Liability Insurance | B78: ='Financial Model'!I86 -> 0 | C78: ='Financial Model'!J86 -> 0 | D78: ='Financial Model'!K86 -> 0 | E78: ='Financial Model'!L86 -> 0 | F78: ='Financial Model'!M86 -> 0 | G78: ='Financial Model'!N86 -> 0 | H78: ='Financial Model'!O86 -> 0 | I78: ='Financial Model'!P86 -> 0 | ... U78: ='Financial Model'!AB86 -> 0
B79: ='Financial Model'!I87 -> 0 | C79: ='Financial Model'!J87 -> 0 | D79: ='Financial Model'!K87 -> 0 | E79: ='Financial Model'!L87 -> 0 | F79: ='Financial Model'!M87 -> 0 | G79: ='Financial Model'!N87 -> 0 | H79: ='Financial Model'!O87 -> 0 | I79: ='Financial Model'!P87 -> 0 | ... U79: ='Financial Model'!AB87 -> 0
B80: ='Financial Model'!I88 -> 0 | C80: ='Financial Model'!J88 -> 0 | D80: ='Financial Model'!K88 -> 0 | E80: ='Financial Model'!L88 -> 0 | F80: ='Financial Model'!M88 -> 250 | G80: ='Financial Model'!N88 -> 1 | H80: ='Financial Model'!O88 -> 1 | I80: ='Financial Model'!P88 -> 1 | ... U80: ='Financial Model'!AB88 -> 1
B81: ='Financial Model'!I89 -> 0 | C81: ='Financial Model'!J89 -> 0 | D81: ='Financial Model'!K89 -> 0 | E81: ='Financial Model'!L89 -> 0 | F81: ='Financial Model'!M89 -> 5000 | G81: ='Financial Model'!N89 -> 1 | H81: ='Financial Model'!O89 -> 1 | I81: ='Financial Model'!P89 -> 1 | ... U81: ='Financial Model'!AB89 -> 1
B82: ='Financial Model'!I90 -> 0 | C82: ='Financial Model'!J90 -> 0 | D82: ='Financial Model'!K90 -> 0 | E82: ='Financial Model'!L90 -> 0 | F82: ='Financial Model'!M90 -> 0 | G82: ='Financial Model'!N90 -> 0 | H82: ='Financial Model'!O90 -> 0 | I82: ='Financial Model'!P90 -> 0 | ... U82: ='Financial Model'!AB90 -> 0
B83: ='Financial Model'!I91 -> 0 | C83: ='Financial Model'!J91 -> 0 | D83: ='Financial Model'!K91 -> 0 | E83: ='Financial Model'!L91 -> -60000 | F83: ='Financial Model'!M91 -> -60000 | G83: ='Financial Model'!N91 -> -115000 | H83: ='Financial Model'!O91 -> -150000 | I83: ='Financial Model'!P91 -> -200000 | ... U83: ='Financial Model'!AB91 -> 0
B84: ='Financial Model'!I92 -> 0 | C84: ='Financial Model'!J92 -> 0 | D84: ='Financial Model'!K92 -> 0 | E84: ='Financial Model'!L92 -> 0 | F84: ='Financial Model'!M92 -> 0 | G84: ='Financial Model'!N92 -> 0 | H84: ='Financial Model'!O92 -> 0 | I84: ='Financial Model'!P92 -> 0 | ... U84: ='Financial Model'!AB92 -> 0
B85: ='Financial Model'!I93 -> 0 | C85: ='Financial Model'!J93 -> 0 | D85: ='Financial Model'!K93 -> 0 | E85: ='Financial Model'!L93 -> -90636.299 | F85: ='Financial Model'!M93 -> -95566.797 | G85: ='Financial Model'!N93 -> -115322.46 | H85: ='Financial Model'!O93 -> -123681.66 | I85: ='Financial Model'!P93 -> -130458.75 | ... U85: ='Financial Model'!AB93 -> 0
B86: ='Financial Model'!I94 -> 0 | C86: ='Financial Model'!J94 -> 0 | D86: ='Financial Model'!K94 -> 0 | E86: ='Financial Model'!L94 -> 0 | F86: ='Financial Model'!M94 -> 0 | G86: ='Financial Model'!N94 -> 0 | H86: ='Financial Model'!O94 -> 0 | I86: ='Financial Model'!P94 -> 0 | ... U86: ='Financial Model'!AB94 -> 0
B87: ='Financial Model'!I95 -> 0 | C87: ='Financial Model'!J95 -> 0 | D87: ='Financial Model'!K95 -> 0 | E87: ='Financial Model'!L95 -> 0 | F87: ='Financial Model'!M95 -> 0 | G87: ='Financial Model'!N95 -> 0 | H87: ='Financial Model'!O95 -> 0 | I87: ='Financial Model'!P95 -> 0 | ... U87: ='Financial Model'!AB95 -> 0
B88: ='Financial Model'!I96 -> 0 | C88: ='Financial Model'!J96 -> 0 | D88: ='Financial Model'!K96 -> 0 | E88: ='Financial Model'!L96 -> 0 | F88: ='Financial Model'!M96 -> 0 | G88: ='Financial Model'!N96 -> 0 | H88: ='Financial Model'!O96 -> 0 | I88: ='Financial Model'!P96 -> 0 | ... U88: ='Financial Model'!AB96 -> 0
B89: ='Financial Model'!I97 -> 0 | C89: ='Financial Model'!J97 -> 0 | D89: ='Financial Model'!K97 -> 0 | E89: ='Financial Model'!L97 -> 0 | F89: ='Financial Model'!M97 -> 0 | G89: ='Financial Model'!N97 -> 0 | H89: ='Financial Model'!O97 -> 0 | I89: ='Financial Model'!P97 -> 0 | ... U89: ='Financial Model'!AB97 -> 0
B90: ='Financial Model'!I98 -> 0 | C90: ='Financial Model'!J98 -> 0 | D90: ='Financial Model'!K98 -> 0 | E90: ='Financial Model'!L98 -> 0 | F90: ='Financial Model'!M98 -> 0 | G90: ='Financial Model'!N98 -> 0 | H90: ='Financial Model'!O98 -> 0 | I90: ='Financial Model'!P98 -> 0 | ... U90: ='Financial Model'!AB98 -> 0
... B93: ='Financial Model'!I101 -> 0 | C93: ='Financial Model'!J101 -> 0 | D93: ='Financial Model'!K101 -> 0 | E93: ='Financial Model'!L101 -> 0 | F93: ='Financial Model'!M101 -> 0 | G93: ='Financial Model'!N101 -> 0 | H93: ='Financial Model'!O101 -> 0 | I93: ='Financial Model'!P101 -> 0 | ... U93: ='Financial Model'!AB101 -> 0

Sheet Profit and Loss
A1: Eqho, LLC
A2: Profit and Loss
A3: January 1 - December 12, 2024
B5: Jan 2024 | C5: Feb 2024 | D5: Mar 2024 | E5: Apr 2024 | F5: May 2024 | G5: Jun 2024 | H5: Jul 2024 | I5: Aug 2024 | J5: Sep 2024 | K5: Oct 2024 | L5: Nov 2024 | M5: Dec 1-12, 2024 | N5: Total
A6: Income
A7: Sales of Product Income | E7: =1646.38 -> 1646.38 | F7: =1453.45 -> 1453.45 | G7: =2209.52 -> 2209.52 | H7: =4351 -> 4351 | I7: =3776.29 -> 3776.29 | J7: =6766.28 -> 6766.28 | K7: =7713.07 -> 7713.07 | L7: =7637.72 -> 7637.72 | M7: =3269.63 -> 3269.63 | N7: =(((((((((((B7)+(C7))+(D7))+(E7))+(F7))+(G7))+(H7))+(I7))+(J7))+(K7))+(L7))+(M7) -> 38823.34
A8: Uncategorized Income | F8: =0.25 -> 0.25 | N8: =(((((((((((B8)+(C8))+(D8))+(E8))+(F8))+(G8))+(H8))+(I8))+(J8))+(K8))+(L8))+(M8) -> 0.25
A9: Total Income | B9: =(B7)+(B8) -> 0 | C9: =(C7)+(C8) -> 0 | D9: =(D7)+(D8) -> 0 | E9: =(E7)+(E8) -> 1646.38 | F9: =(F7)+(F8) -> 1453.7 | G9: =(G7)+(G8) -> 2209.52 | H9: =(H7)+(H8) -> 4351 | I9: =(I7)+(I8) -> 3776.29 | ... M9: =(M7)+(M8) -> 3269.63 | N9: =(((((((((((B9)+(C9))+(D9))+(E9))+(F9))+(G9))+(H9))+(I9))+(J9))+(K9))+(L9))+(M9) -> 38823.59 | P9: =SUM(B9:K9)/11 -> 2537.84
A10: Cost of Goods Sold | P10: =SUM(B10:K10)/11 -> 0
A11: Cloud Services | B11: =165.59 -> 165.59 | C11: =551.59 -> 551.59 | D11: =1590.99 -> 1590.99 | E11: =768.33 -> 768.33 | F11: =2692.83 -> 2692.83 | G11: =1236.67 -> 1236.67 | H11: =3428.37 -> 3428.37 | I11: =4061.47 -> 4061.47 | J11: =1212.47 -> 1212.47 | K11: =3162.95 -> 3162.95 | L11: =5485.06 -> 5485.06 | N11: =(((((((((((B11)+(C11))+(D11))+(E11))+(F11))+(G11))+(H11))+(I11))+(J11))+(K11))+(L11))+(M11) -> 24356.32 | P11: =SUM(B11:K11)/11 -> 1715.5691
A12: Software - COGS | B12: =38.51 -> 38.51 | C12: =47.71 -> 47.71 | D12: =307.55 -> 307.55 | E12: =1114.73 -> 1114.73 | F12: =4599.22 -> 4599.22 | G12: =2611.56 -> 2611.56 | H12: =3514.2 -> 3514.2 | I12: =1420.44 -> 1420.44 | J12: =2387.05 -> 2387.05 | K12: =2093.47 -> 2093.47 | L12: =52.61 -> 52.61 | N12: =(((((((((((B12)+(C12))+(D12))+(E12))+(F12))+(G12))+(H12))+(I12))+(J12))+(K12))+(L12))+(M12) -> 18187.05 | P12: =SUM(B12:K12)/11 -> 1648.5855
A13: Software - Tools | B13: =297.03 -> 297.03 | C13: =338.2 -> 338.2 | D13: =340.13 -> 340.13 | E13: =394.31 -> 394.31 | F13: =560.44 -> 560.44 | G13: =551.54 -> 551.54 | H13: =762.6 -> 762.6 | I13: =1791.57 -> 1791.57 | J13: =993.13 -> 993.13 | K13: =1085.62 -> 1085.62 | L13: =944.76 -> 944.76 | N13: =(((((((((((B13)+(C13))+(D13))+(E13))+(F13))+(G13))+(H13))+(I13))+(J13))+(K13))+(L13))+(M13) -> 8059.33 | P13: =SUM(B13:K13)/11 -> 646.77909
A14: Voice AI Provider | B14: =908.32 -> 908.32 | C14: =330 -> 330 | D14: =330 -> 330 | E14: =511.37 -> 511.37 | F14: =1387.79 -> 1387.79 | G14: =859.8 -> 859.8 | H14: =1599.82 -> 1599.82 | I14: =945.81 -> 945.81 | J14: =534.78 -> 534.78 | K14: =708.64 -> 708.64 | N14: =(((((((((((B14)+(C14))+(D14))+(E14))+(F14))+(G14))+(H14))+(I14))+(J14))+(K14))+(L14))+(M14) -> 8116.33 | P14: =SUM(B14:K14)/11 -> 737.84818
A15: Total Software - COGS | B15: =((B12)+(B13))+(B14) -> 1243.86 | C15: =((C12)+(C13))+(C14) -> 715.91 | D15: =((D12)+(D13))+(D14) -> 977.68 | E15: =((E12)+(E13))+(E14) -> 2020.41 | F15: =((F12)+(F13))+(F14) -> 6547.45 | G15: =((G12)+(G13))+(G14) -> 4022.9 | H15: =((H12)+(H13))+(H14) -> 5876.62 | I15: =((I12)+(I13))+(I14) -> 4157.82 | ... M15: =((M12)+(M13))+(M14) -> 0 | N15: =(((((((((((B15)+(C15))+(D15))+(E15))+(F15))+(G15))+(H15))+(I15))+(J15))+(K15))+(L15))+(M15) -> 34362.71 | P15: =SUM(B15:K15)/11 -> 3033.2127
A16: Telephony Carriers | B16: =151.26 -> 151.26 | C16: =75.86 -> 75.86 | D16: =301.96 -> 301.96 | E16: =309.86 -> 309.86 | F16: =2514.17 -> 2514.17 | G16: =1464.9 -> 1464.9 | H16: =2828.47 -> 2828.47 | I16: =1369.6 -> 1369.6 | J16: =1945.58 -> 1945.58 | K16: =2833.65 -> 2833.65 | L16: =1258.78 -> 1258.78 | N16: =(((((((((((B16)+(C16))+(D16))+(E16))+(F16))+(G16))+(H16))+(I16))+(J16))+(K16))+(L16))+(M16) -> 15054.09 | P16: =SUM(B16:K16)/11 -> 1254.1191
A17: Total Cost of Goods Sold | B17: =((B11)+(B15))+(B16) -> 1560.71 | C17: =((C11)+(C15))+(C16) -> 1343.36 | D17: =((D11)+(D15))+(D16) -> 2870.63 | E17: =((E11)+(E15))+(E16) -> 3098.6 | F17: =((F11)+(F15))+(F16) -> 11754.45 | G17: =((G11)+(G15))+(G16) -> 6724.47 | H17: =((H11)+(H15))+(H16) -> 12133.46 | I17: =((I11)+(I15))+(I16) -> 9588.89 | ... M17: =((M11)+(M15))+(M16) -> 0 | N17: =(((((((((((B17)+(C17))+(D17))+(E17))+(F17))+(G17))+(H17))+(I17))+(J17))+(K17))+(L17))+(M17) -> 73773.12 | P17: =SUM(B17:K17)/11 -> 6002.9009
A18: Gross Profit | B18: =(B9)-(B17) -> -1560.71 | C18: =(C9)-(C17) -> -1343.36 | D18: =(D9)-(D17) -> -2870.63 | E18: =(E9)-(E17) -> -1452.22 | F18: =(F9)-(F17) -> -10300.75 | G18: =(G9)-(G17) -> -4514.95 | H18: =(H9)-(H17) -> -7782.46 | I18: =(I9)-(I17) -> -5812.6 | ... M18: =(M9)-(M17) -> 3269.63 | N18: =(((((((((((B18)+(C18))+(D18))+(E18))+(F18))+(G18))+(H18))+(I18))+(J18))+(K18))+(L18))+(M18) -> -34949.53 | P18: =SUM(B18:K18)/11 -> -3465.0609
A19: Expenses | P19: =SUM(B19:K19)/11 -> 0
A20: Advertising & marketing | N20: =(((((((((((B20)+(C20))+(D20))+(E20))+(F20))+(G20))+(H20))+(I20))+(J20))+(K20))+(L20))+(M20) -> 0 | P20: =SUM(B20:K20)/11 -> 0
A21: Content Creation | B21: =2893.05 -> 2893.05 | N21: =(((((((((((B21)+(C21))+(D21))+(E21))+(F21))+(G21))+(H21))+(I21))+(J21))+(K21))+(L21))+(M21) -> 2893.05 | P21: =SUM(B21:K21)/11 -> 263.00455
A22: Listing fees | B22: =6.67 -> 6.67 | N22: =(((((((((((B22)+(C22))+(D22))+(E22))+(F22))+(G22))+(H22))+(I22))+(J22))+(K22))+(L22))+(M22) -> 6.67 | P22: =SUM(B22:K22)/11 -> 0.60636364
A23: Social media | C23: =347.32 -> 347.32 | D23: =1887.16 -> 1887.16 | E23: =1859 -> 1859 | F23: =1197.13 -> 1197.13 | G23: =1189.4 -> 1189.4 | H23: =1208.67 -> 1208.67 | I23: =230.38 -> 230.38 | J23: =41.12 -> 41.12 | K23: =848.44 -> 848.44 | L23: =856.68 -> 856.68 | N23: =(((((((((((B23)+(C23))+(D23))+(E23))+(F23))+(G23))+(H23))+(I23))+(J23))+(K23))+(L23))+(M23) -> 9665.3 | P23: =SUM(B23:K23)/11 -> 800.78364
A24: Software Marketing Tools | L24: =63.34 -> 63.34 | N24: =(((((((((((B24)+(C24))+(D24))+(E24))+(F24))+(G24))+(H24))+(I24))+(J24))+(K24))+(L24))+(M24) -> 63.34 | P24: =SUM(B24:K24)/11 -> 0
A25: Trade Shows | B25: =499.9 -> 499.9 | E25: =2331.68 -> 2331.68 | N25: =(((((((((((B25)+(C25))+(D25))+(E25))+(F25))+(G25))+(H25))+(I25))+(J25))+(K25))+(L25))+(M25) -> 2831.58 | P25: =SUM(B25:K25)/11 -> 257.41636
A26: Total Advertising & marketing | B26: =(((((B20)+(B21))+(B22))+(B23))+(B24))+(B25) -> 3399.62 | C26: =(((((C20)+(C21))+(C22))+(C23))+(C24))+(C25) -> 347.32 | D26: =(((((D20)+(D21))+(D22))+(D23))+(D24))+(D25) -> 1887.16 | E26: =(((((E20)+(E21))+(E22))+(E23))+(E24))+(E25) -> 4190.68 | F26: =(((((F20)+(F21))+(F22))+(F23))+(F24))+(F25) -> 1197.13 | G26: =(((((G20)+(G21))+(G22))+(G23))+(G24))+(G25) -> 1189.4 | H26: =(((((H20)+(H21))+(H22))+(H23))+(H24))+(H25) -> 1208.67 | I26: =(((((I20)+(I21))+(I22))+(I23))+(I24))+(I25) -> 230.38 | ... M26: =(((((M20)+(M21))+(M22))+(M23))+(M24))+(M25) -> 0 | N26: =(((((((((((B26)+(C26))+(D26))+(E26))+(F26))+(G26))+(H26))+(I26))+(J26))+(K26))+(L26))+(M26) -> 15459.94 | P26: =SUM(B26:K26)/11 -> 1321.8109
A27: Contract labor | B27: =51247.34 -> 51247.34 | C27: =46435.67 -> 46435.67 | D27: =67432.96 -> 67432.96 | E27: =50047.19 -> 50047.19 | F27: =68246.24 -> 68246.24 | G27: =81559.87 -> 81559.87 | H27: =84427.72 -> 84427.72 | I27: =78022.99 -> 78022.99 | J27: =29145.26 -> 29145.26 | K27: =34714.45 -> 34714.45 | L27: =41221.67 -> 41221.67 | M27: =5427.89 -> 5427.89 | N27: =(((((((((((B27)+(C27))+(D27))+(E27))+(F27))+(G27))+(H27))+(I27))+(J27))+(K27))+(L27))+(M27) -> 637929.25 | P27: =SUM(B27:K27)/11 -> 53752.699
A28: Upwork | E28: =789.23 -> 789.23 | F28: =-214.95 -> -214.95 | N28: =(((((((((((B28)+(C28))+(D28))+(E28))+(F28))+(G28))+(H28))+(I28))+(J28))+(K28))+(L28))+(M28) -> 574.28 | P28: =SUM(B28:K28)/11 -> 52.207273
A29: Total Contract labor | B29: =(B27)+(B28) -> 51247.34 | C29: =(C27)+(C28) -> 46435.67 | D29: =(D27)+(D28) -> 67432.96 | E29: =(E27)+(E28) -> 50836.42 | F29: =(F27)+(F28) -> 68031.29 | G29: =(G27)+(G28) -> 81559.87 | H29: =(H27)+(H28) -> 84427.72 | I29: =(I27)+(I28) -> 78022.99 | ... M29: =(M27)+(M28) -> 5427.89 | N29: =(((((((((((B29)+(C29))+(D29))+(E29))+(F29))+(G29))+(H29))+(I29))+(J29))+(K29))+(L29))+(M29) -> 638503.53 | P29: =SUM(B29:K29)/11 -> 53804.906
A30: General business expenses | N30: =(((((((((((B30)+(C30))+(D30))+(E30))+(F30))+(G30))+(H30))+(I30))+(J30))+(K30))+(L30))+(M30) -> 0 | P30: =SUM(B30:K30)/11 -> 0
A31: Bank fees & service charges | B31: =25 -> 25 | D31: =50 -> 50 | E31: =50 -> 50 | F31: =65 -> 65 | G31: =160 -> 160 | H31: =240 -> 240 | I31: =505 -> 505 | J31: =120 -> 120 | K31: =120 -> 120 | L31: =280 -> 280 | N31: =(((((((((((B31)+(C31))+(D31))+(E31))+(F31))+(G31))+(H31))+(I31))+(J31))+(K31))+(L31))+(M31) -> 1615 | P31: =SUM(B31:K31)/11 -> 121.36364
A32: Total General business expenses | B32: =(B30)+(B31) -> 25 | C32: =(C30)+(C31) -> 0 | D32: =(D30)+(D31) -> 50 | E32: =(E30)+(E31) -> 50 | F32: =(F30)+(F31) -> 65 | G32: =(G30)+(G31) -> 160 | H32: =(H30)+(H31) -> 240 | I32: =(I30)+(I31) -> 505 | ... M32: =(M30)+(M31) -> 0 | N32: =(((((((((((B32)+(C32))+(D32))+(E32))+(F32))+(G32))+(H32))+(I32))+(J32))+(K32))+(L32))+(M32) -> 1615 | P32: =SUM(B32:K32)/11 -> 121.36364
A33: Legal & accounting services | N33: =(((((((((((B33)+(C33))+(D33))+(E33))+(F33))+(G33))+(H33))+(I33))+(J33))+(K33))+(L33))+(M33) -> 0 | P33: =SUM(B33:K33)/11 -> 0
A34: Legal Fees | I34: =1800 -> 1800 | J34: =1800 -> 1800 | K34: =1800 -> 1800 | L34: =1800 -> 1800 | N34: =(((((((((((B34)+(C34))+(D34))+(E34))+(F34))+(G34))+(H34))+(I34))+(J34))+(K34))+(L34))+(M34) -> 7200 | P34: =SUM(B34:K34)/11 -> 490.90909
A35: Total Legal & accounting services | B35: =(B33)+(B34) -> 0 | C35: =(C33)+(C34) -> 0 | D35: =(D33)+(D34) -> 0 | E35: =(E33)+(E34) -> 0 | F35: =(F33)+(F34) -> 0 | G35: =(G33)+(G34) -> 0 | H35: =(H33)+(H34) -> 0 | I35: =(I33)+(I34) -> 1800 | ... M35: =(M33)+(M34) -> 0 | N35: =(((((((((((B35)+(C35))+(D35))+(E35))+(F35))+(G35))+(H35))+(I35))+(J35))+(K35))+(L35))+(M35) -> 7200 | P35: =SUM(B35:K35)/11 -> 490.90909
A36: Meals | B36: =160.43 -> 160.43 | E36: =34.47 -> 34.47 | G36: =14.39 -> 14.39 | H36: =26 -> 26 | I36: =14.7 -> 14.7 | J36: =47.54 -> 47.54 | N36: =(((((((((((B36)+(C36))+(D36))+(E36))+(F36))+(G36))+(H36))+(I36))+(J36))+(K36))+(L36))+(M36) -> 297.53 | P36: =SUM(B36:K36)/11 -> 27.048182
A37: Meals - Guzman | D37: =141.89 -> 141.89 | E37: =190.1 -> 190.1 | G37: =210.79 -> 210.79 | H37: =216.84 -> 216.84 | N37: =(((((((((((B37)+(C37))+(D37))+(E37))+(F37))+(G37))+(H37))+(I37))+(J37))+(K37))+(L37))+(M37) -> 759.62 | P37: =SUM(B37:K37)/11 -> 69.056364
A38: Meals with clients | B38: =1780.44 -> 1780.44 | C38: =280.94 -> 280.94 | D38: =219.79 -> 219.79 | E38: =145.66 -> 145.66 | F38: =169.56 -> 169.56 | G38: =106.8 -> 106.8 | H38: =387.56 -> 387.56 | I38: =453.29 -> 453.29 | J38: =389.7 -> 389.7 | K38: =499.47 -> 499.47 | L38: =245.5 -> 245.5 | M38: =23.94 -> 23.94 | N38: =(((((((((((B38)+(C38))+(D38))+(E38))+(F38))+(G38))+(H38))+(I38))+(J38))+(K38))+(L38))+(M38) -> 4702.65 | P38: =SUM(B38:K38)/11 -> 403.01909
A39: Travel meals | B39: =57.15 -> 57.15 | C39: =20.68 -> 20.68 | N39: =(((((((((((B39)+(C39))+(D39))+(E39))+(F39))+(G39))+(H39))+(I39))+(J39))+(K39))+(L39))+(M39) -> 77.83 | P39: =SUM(B39:K39)/11 -> 7.0754545
A40: Total Meals | B40: =(((B36)+(B37))+(B38))+(B39) -> 1998.02 | C40: =(((C36)+(C37))+(C38))+(C39) -> 301.62 | D40: =(((D36)+(D37))+(D38))+(D39) -> 361.68 | E40: =(((E36)+(E37))+(E38))+(E39) -> 370.23 | F40: =(((F36)+(F37))+(F38))+(F39) -> 169.56 | G40: =(((G36)+(G37))+(G38))+(G39) -> 331.98 | H40: =(((H36)+(H37))+(H38))+(H39) -> 630.4 | I40: =(((I36)+(I37))+(I38))+(I39) -> 467.99 | ... M40: =(((M36)+(M37))+(M38))+(M39) -> 23.94 | N40: =(((((((((((B40)+(C40))+(D40))+(E40))+(F40))+(G40))+(H40))+(I40))+(J40))+(K40))+(L40))+(M40) -> 5837.63 | P40: =SUM(B40:K40)/11 -> 506.19909
A41: Office expenses | N41: =(((((((((((B41)+(C41))+(D41))+(E41))+(F41))+(G41))+(H41))+(I41))+(J41))+(K41))+(L41))+(M41) -> 0 | P41: =SUM(B41:K41)/11 -> 0
A42: Software & apps | B42: =444.09 -> 444.09 | C42: =790.84 -> 790.84 | D42: =1110.01 -> 1110.01 | E42: =1595.33 -> 1595.33 | F42: =1970.52 -> 1970.52 | G42: =2384.4 -> 2384.4 | H42: =2400.5 -> 2400.5 | I42: =4691.39 -> 4691.39 | J42: =3233.65 -> 3233.65 | K42: =5776.56 -> 5776.56 | L42: =4477.18 -> 4477.18 | M42: =793.9 -> 793.9 | N42: =(((((((((((B42)+(C42))+(D42))+(E42))+(F42))+(G42))+(H42))+(I42))+(J42))+(K42))+(L42))+(M42) -> 29668.37 | P42: =SUM(B42:K42)/11 -> 2217.9355
A43: Ai Software Tools - Not COGS | B43: =21.47 -> 21.47 | C43: =85.88 -> 85.88 | D43: =85.88 -> 85.88 | E43: =85.88 -> 85.88 | G43: =85.88 -> 85.88 | H43: =21.47 -> 21.47 | I43: =85.88 -> 85.88 | J43: =85.88 -> 85.88 | K43: =85.88 -> 85.88 | L43: =237.99 -> 237.99 | N43: =(((((((((((B43)+(C43))+(D43))+(E43))+(F43))+(G43))+(H43))+(I43))+(J43))+(K43))+(L43))+(M43) -> 882.09 | P43: =SUM(B43:K43)/11 -> 58.554545
A44: Total Software & apps | B44: =(B42)+(B43) -> 465.56 | C44: =(C42)+(C43) -> 876.72 | D44: =(D42)+(D43) -> 1195.89 | E44: =(E42)+(E43) -> 1681.21 | F44: =(F42)+(F43) -> 1970.52 | G44: =(G42)+(G43) -> 2470.28 | H44: =(H42)+(H43) -> 2421.97 | I44: =(I42)+(I43) -> 4777.27 | ... M44: =(M42)+(M43) -> 793.9 | N44: =(((((((((((B44)+(C44))+(D44))+(E44))+(F44))+(G44))+(H44))+(I44))+(J44))+(K44))+(L44))+(M44) -> 30550.46 | P44: =SUM(B44:K44)/11 -> 2276.49
A45: Total Office expenses | B45: =(B41)+(B44) -> 465.56 | C45: =(C41)+(C44) -> 876.72 | D45: =(D41)+(D44) -> 1195.89 | E45: =(E41)+(E44) -> 1681.21 | F45: =(F41)+(F44) -> 1970.52 | G45: =(G41)+(G44) -> 2470.28 | H45: =(H41)+(H44) -> 2421.97 | I45: =(I41)+(I44) -> 4777.27 | ... M45: =(M41)+(M44) -> 793.9 | N45: =(((((((((((B45)+(C45))+(D45))+(E45))+(F45))+(G45))+(H45))+(I45))+(J45))+(K45))+(L45))+(M45) -> 30550.46 | P45: =SUM(B45:K45)/11 -> 2276.49
A46: Travel | B46: =1093.56 -> 1093.56 | E46: =398.79 -> 398.79 | N46: =(((((((((((B46)+(C46))+(D46))+(E46))+(F46))+(G46))+(H46))+(I46))+(J46))+(K46))+(L46))+(M46) -> 1492.35 | P46: =SUM(B46:K46)/11 -> 135.66818
A47: Airfare | B47: =198.2 -> 198.2 | N47: =(((((((((((B47)+(C47))+(D47))+(E47))+(F47))+(G47))+(H47))+(I47))+(J47))+(K47))+(L47))+(M47) -> 198.2 | P47: =SUM(B47:K47)/11 -> 18.018182
A48: Hotels | B48: =1124.41 -> 1124.41 | E48: =755.1 -> 755.1 | N48: =(((((((((((B48)+(C48))+(D48))+(E48))+(F48))+(G48))+(H48))+(I48))+(J48))+(K48))+(L48))+(M48) -> 1879.51 | P48: =SUM(B48:K48)/11 -> 170.86455
A49: Total Travel | B49: =((B46)+(B47))+(B48) -> 2416.17 | C49: =((C46)+(C47))+(C48) -> 0 | D49: =((D46)+(D47))+(D48) -> 0 | E49: =((E46)+(E47))+(E48) -> 1153.89 | F49: =((F46)+(F47))+(F48) -> 0 | G49: =((G46)+(G47))+(G48) -> 0 | H49: =((H46)+(H47))+(H48) -> 0 | I49: =((I46)+(I47))+(I48) -> 0 | ... M49: =((M46)+(M47))+(M48) -> 0 | N49: =(((((((((((B49)+(C49))+(D49))+(E49))+(F49))+(G49))+(H49))+(I49))+(J49))+(K49))+(L49))+(M49) -> 3570.06 | P49: =SUM(B49:K49)/11 -> 324.55091
A50: Total Expenses | B50: =((((((B26)+(B29))+(B32))+(B35))+(B40))+(B45))+(B49) -> 59551.71 | C50: =((((((C26)+(C29))+(C32))+(C35))+(C40))+(C45))+(C49) -> 47961.33 | D50: =((((((D26)+(D29))+(D32))+(D35))+(D40))+(D45))+(D49) -> 70927.69 | E50: =((((((E26)+(E29))+(E32))+(E35))+(E40))+(E45))+(E49) -> 58282.43 | F50: =((((((F26)+(F29))+(F32))+(F35))+(F40))+(F45))+(F49) -> 71433.5 | G50: =((((((G26)+(G29))+(G32))+(G35))+(G40))+(G45))+(G49) -> 85711.53 | H50: =((((((H26)+(H29))+(H32))+(H35))+(H40))+(H45))+(H49) -> 88928.76 | I50: =((((((I26)+(I29))+(I32))+(I35))+(I40))+(I45))+(I49) -> 85803.63 | ... M50: =((((((M26)+(M29))+(M32))+(M35))+(M40))+(M45))+(M49) -> 6245.73 | N50: =(((((((((((B50)+(C50))+(D50))+(E50))+(F50))+(G50))+(H50))+(I50))+(J50))+(K50))+(L50))+(M50) -> 702736.62 | P50: =SUM(B50:K50)/11 -> 58846.23
A51: Net Operating Income | B51: =(B18)-(B50) -> -61112.42 | C51: =(C18)-(C50) -> -49304.69 | D51: =(D18)-(D50) -> -73798.32 | E51: =(E18)-(E50) -> -59734.65 | F51: =(F18)-(F50) -> -81734.25 | G51: =(G18)-(G50) -> -90226.48 | H51: =(H18)-(H50) -> -96711.22 | I51: =(I18)-(I50) -> -91616.23 | ... M51: =(M18)-(M50) -> -2976.1 | N51: =(((((((((((B51)+(C51))+(D51))+(E51))+(F51))+(G51))+(H51))+(I51))+(J51))+(K51))+(L51))+(M51) -> -737686.15 | P51: =SUM(B51:K51)/11 -> -62311.291
A52: Other Expenses
A53: Vehicle expenses | N53: =(((((((((((B53)+(C53))+(D53))+(E53))+(F53))+(G53))+(H53))+(I53))+(J53))+(K53))+(L53))+(M53) -> 0
A54: Parking & tolls | B54: =210 -> 210 | E54: =105 -> 105 | N54: =(((((((((((B54)+(C54))+(D54))+(E54))+(F54))+(G54))+(H54))+(I54))+(J54))+(K54))+(L54))+(M54) -> 315
A55: Vehicle gas & fuel | B55: =36.34 -> 36.34 | C55: =10.3 -> 10.3 | D55: =17.8 -> 17.8 | E55: =13.55 -> 13.55 | F55: =36.76 -> 36.76 | G55: =5.75 -> 5.75 | H55: =39.28 -> 39.28 | I55: =27.48 -> 27.48 | J55: =80.18 -> 80.18 | K55: =66.44 -> 66.44 | L55: =80.89 -> 80.89 | N55: =(((((((((((B55)+(C55))+(D55))+(E55))+(F55))+(G55))+(H55))+(I55))+(J55))+(K55))+(L55))+(M55) -> 414.77
A56: Total Vehicle expenses | B56: =((B53)+(B54))+(B55) -> 246.34 | C56: =((C53)+(C54))+(C55) -> 10.3 | D56: =((D53)+(D54))+(D55) -> 17.8 | E56: =((E53)+(E54))+(E55) -> 118.55 | F56: =((F53)+(F54))+(F55) -> 36.76 | G56: =((G53)+(G54))+(G55) -> 5.75 | H56: =((H53)+(H54))+(H55) -> 39.28 | I56: =((I53)+(I54))+(I55) -> 27.48 | ... M56: =((M53)+(M54))+(M55) -> 0 | N56: =(((((((((((B56)+(C56))+(D56))+(E56))+(F56))+(G56))+(H56))+(I56))+(J56))+(K56))+(L56))+(M56) -> 729.77
A57: Total Other Expenses | B57: =B56 -> 246.34 | C57: =C56 -> 10.3 | D57: =D56 -> 17.8 | E57: =E56 -> 118.55 | F57: =F56 -> 36.76 | G57: =G56 -> 5.75 | H57: =H56 -> 39.28 | I57: =I56 -> 27.48 | ... M57: =M56 -> 0 | N57: =(((((((((((B57)+(C57))+(D57))+(E57))+(F57))+(G57))+(H57))+(I57))+(J57))+(K57))+(L57))+(M57) -> 729.77
A58: Net Other Income | B58: =(0)-(B57) -> -246.34 | C58: =(0)-(C57) -> -10.3 | D58: =(0)-(D57) -> -17.8 | E58: =(0)-(E57) -> -118.55 | F58: =(0)-(F57) -> -36.76 | G58: =(0)-(G57) -> -5.75 | H58: =(0)-(H57) -> -39.28 | I58: =(0)-(I57) -> -27.48 | ... M58: =(0)-(M57) -> 0 | N58: =(((((((((((B58)+(C58))+(D58))+(E58))+(F58))+(G58))+(H58))+(I58))+(J58))+(K58))+(L58))+(M58) -> -729.77
A59: Net Income | B59: =(B51)+(B58) -> -61358.76 | C59: =(C51)+(C58) -> -49314.99 | D59: =(D51)+(D58) -> -73816.12 | E59: =(E51)+(E58) -> -59853.2 | F59: =(F51)+(F58) -> -81771.01 | G59: =(G51)+(G58) -> -90232.23 | H59: =(H51)+(H58) -> -96750.5 | I59: =(I51)+(I58) -> -91643.71 | ... M59: =(M51)+(M58) -> -2976.1 | N59: =(((((((((((B59)+(C59))+(D59))+(E59))+(F59))+(G59))+(H59))+(I59))+(J59))+(K59))+(L59))+(M59) -> -738415.92
A63: Thursday, Dec 12, 2024 01:33:15 PM GMT-8 - Accrual Basis
